{"rsn":"Eg_Tiagosd","overall":{"rank":1666,"level":2595,"exp":1054027033,"isSkill":true},"attack":{"rank":3713,"level":99,"exp":56247955,"isSkill":true},"defence":{"rank":3334,"level":99,"exp":56264480,"isSkill":true},"strength":{"rank":2531,"level":99,"exp":75038514,"isSkill":true},"constitution":{"rank":1337,"level":99,"exp":101082006,"isSkill":true},"ranged":{"rank":1019,"level":99,"exp":78028631,"isSkill":true},"prayer":{"rank":4394,"level":99,"exp":17295698,"isSkill":true},"magic":{"rank":2771,"level":99,"exp":58268784,"isSkill":true},"cooking":{"rank":8897,"level":99,"exp":23064597,"isSkill":true},"woodcutting":{"rank":18977,"level":99,"exp":18412131,"isSkill":true},"fletching":{"rank":11989,"level":99,"exp":16285406,"isSkill":true},"fishing":{"rank":12471,"level":99,"exp":19823857,"isSkill":true},"firemaking":{"rank":4366,"level":99,"exp":29219721,"isSkill":true},"crafting":{"rank":10764,"level":99,"exp":15951551,"isSkill":true},"smithing":{"rank":6857,"level":99,"exp":17279832,"isSkill":true},"mining":{"rank":11223,"level":99,"exp":16757591,"isSkill":true},"herblore":{"rank":2234,"level":99,"exp":26773583,"isSkill":true},"agility":{"rank":3155,"level":99,"exp":19238381,"isSkill":true},"thieving":{"rank":8476,"level":99,"exp":16318329,"isSkill":true},"slayer":{"rank":984,"level":99,"exp":54114895,"isSkill":true},"farming":{"rank":4751,"level":99,"exp":22308507,"isSkill":true},"runecrafting":{"rank":6082,"level":99,"exp":18892896,"isSkill":true},"hunter":{"rank":3237,"level":99,"exp":22907006,"isSkill":true},"construction":{"rank":6030,"level":99,"exp":18336435,"isSkill":true},"summoning":{"rank":1097,"level":99,"exp":42746657,"isSkill":true},"dungeoneering":{"rank":2746,"level":120,"exp":196569528,"isSkill":true},"divination":{"rank":3477,"level":99,"exp":16800062,"isSkill":true},"bounty_hunter":{"rank":-1,"score":-1,"isSkill":false},"bounty_hunter_rouges":{"rank":-1,"score":-1,"isSkill":false},"dominion_tower":{"rank":4560,"score":5444047,"isSkill":false},"crucible":{"rank":-1,"score":-1,"isSkill":false},"castle_wars":{"rank":-1,"score":-1,"isSkill":false},"BA_attackers":{"rank":27147,"score":2005,"isSkill":false},"BA_defenders":{"rank":21065,"score":1786,"isSkill":false},"BA_collectors":{"rank":22069,"score":1821,"isSkill":false},"BA_healers":{"rank":45270,"score":1924,"isSkill":false},"duel_tournaments":{"rank":-1,"score":-1,"isSkill":false},"mobilising_armies":{"rank":5159,"score":352,"isSkill":false},"conquest":{"rank":28515,"score":1256,"isSkill":false},"fist_of_guthix":{"rank":-1,"score":-1,"isSkill":false},"GG_resource":{"rank":-1,"score":-1,"isSkill":false},"GG_athletics":{"rank":-1,"score":-1,"isSkill":false},"we2":{"rank":-1,"score":-1,"isSkill":false},"heist_guard":{"rank":-1,"score":-1,"isSkill":false},"heist_robber":{"rank":-1,"score":-1,"isSkill":false},"CFP":{"rank":28995,"score":49,"isSkill":false}}