{"rsn":"King_Of_Surf","overall":{"rank":208874,"level":1985,"exp":136916600,"isSkill":true},"attack":{"rank":129464,"level":99,"exp":13185588,"isSkill":true},"defence":{"rank":61263,"level":99,"exp":16381266,"isSkill":true},"strength":{"rank":146954,"level":99,"exp":13375941,"isSkill":true},"constitution":{"rank":116763,"level":99,"exp":16828542,"isSkill":true},"ranged":{"rank":160438,"level":93,"exp":7724479,"isSkill":true},"prayer":{"rank":203606,"level":80,"exp":2023256,"isSkill":true},"magic":{"rank":267439,"level":90,"exp":5713700,"isSkill":true},"cooking":{"rank":147621,"level":99,"exp":13119430,"isSkill":true},"woodcutting":{"rank":80194,"level":99,"exp":13811665,"isSkill":true},"fletching":{"rank":157218,"level":93,"exp":7453638,"isSkill":true},"fishing":{"rank":78496,"level":99,"exp":13094464,"isSkill":true},"firemaking":{"rank":271338,"level":81,"exp":2249427,"isSkill":true},"crafting":{"rank":417083,"level":61,"exp":322598,"isSkill":true},"smithing":{"rank":501113,"level":56,"exp":196326,"isSkill":true},"mining":{"rank":645047,"level":59,"exp":251188,"isSkill":true},"herblore":{"rank":373441,"level":54,"exp":165880,"isSkill":true},"agility":{"rank":259400,"level":68,"exp":624922,"isSkill":true},"thieving":{"rank":71013,"level":90,"exp":5445343,"isSkill":true},"slayer":{"rank":178970,"level":81,"exp":2299912,"isSkill":true},"farming":{"rank":428062,"level":42,"exp":45719,"isSkill":true},"runecrafting":{"rank":187104,"level":74,"exp":1149415,"isSkill":true},"hunter":{"rank":286687,"level":65,"exp":494098,"isSkill":true},"construction":{"rank":500104,"level":42,"exp":45806,"isSkill":true},"summoning":{"rank":243917,"level":70,"exp":753726,"isSkill":true},"dungeoneering":{"rank":510528,"level":42,"exp":46314,"isSkill":true},"divination":{"rank":180896,"level":51,"exp":113957,"isSkill":true},"bounty_hunter":{"rank":-1,"score":-1,"isSkill":false},"bounty_hunter_rouges":{"rank":-1,"score":-1,"isSkill":false},"dominion_tower":{"rank":-1,"score":-1,"isSkill":false},"crucible":{"rank":-1,"score":-1,"isSkill":false},"castle_wars":{"rank":-1,"score":-1,"isSkill":false},"BA_attackers":{"rank":-1,"score":-1,"isSkill":false},"BA_defenders":{"rank":-1,"score":-1,"isSkill":false},"BA_collectors":{"rank":-1,"score":-1,"isSkill":false},"BA_healers":{"rank":-1,"score":-1,"isSkill":false},"duel_tournaments":{"rank":-1,"score":-1,"isSkill":false},"mobilising_armies":{"rank":-1,"score":-1,"isSkill":false},"conquest":{"rank":-1,"score":-1,"isSkill":false},"fist_of_guthix":{"rank":-1,"score":-1,"isSkill":false},"GG_resource":{"rank":-1,"score":-1,"isSkill":false},"GG_athletics":{"rank":145443,"score":495,"isSkill":false},"we2":{"rank":-1,"score":-1,"isSkill":false},"heist_guard":{"rank":-1,"score":-1,"isSkill":false},"heist_robber":{"rank":-1,"score":-1,"isSkill":false},"CFP":{"rank":-1,"score":-1,"isSkill":false}}