{"rsn":"skauwbro","overall":{"rank":22787,"level":2554,"exp":451218104,"isSkill":true},"attack":{"rank":17401,"level":99,"exp":31065902,"isSkill":true},"defence":{"rank":13811,"level":99,"exp":30892914,"isSkill":true},"strength":{"rank":23605,"level":99,"exp":31135266,"isSkill":true},"constitution":{"rank":19142,"level":99,"exp":41492850,"isSkill":true},"ranged":{"rank":31920,"level":99,"exp":20017922,"isSkill":true},"prayer":{"rank":28328,"level":99,"exp":13935898,"isSkill":true},"magic":{"rank":54062,"level":99,"exp":17157358,"isSkill":true},"cooking":{"rank":18375,"level":99,"exp":18109372,"isSkill":true},"woodcutting":{"rank":71934,"level":99,"exp":14027225,"isSkill":true},"fletching":{"rank":36610,"level":99,"exp":14015394,"isSkill":true},"fishing":{"rank":75737,"level":99,"exp":13131441,"isSkill":true},"firemaking":{"rank":33698,"level":99,"exp":14666851,"isSkill":true},"crafting":{"rank":24973,"level":99,"exp":14010824,"isSkill":true},"smithing":{"rank":40882,"level":99,"exp":13176476,"isSkill":true},"mining":{"rank":47927,"level":99,"exp":13034603,"isSkill":true},"herblore":{"rank":56239,"level":99,"exp":13238563,"isSkill":true},"agility":{"rank":31421,"level":99,"exp":13209023,"isSkill":true},"thieving":{"rank":28069,"level":99,"exp":13612768,"isSkill":true},"slayer":{"rank":23507,"level":99,"exp":15244766,"isSkill":true},"farming":{"rank":29798,"level":99,"exp":13703281,"isSkill":true},"runecrafting":{"rank":50433,"level":99,"exp":13069514,"isSkill":true},"hunter":{"rank":44773,"level":97,"exp":11364936,"isSkill":true},"construction":{"rank":30138,"level":99,"exp":13423439,"isSkill":true},"summoning":{"rank":5285,"level":99,"exp":18016361,"isSkill":true},"dungeoneering":{"rank":34994,"level":105,"exp":25233093,"isSkill":true},"divination":{"rank":85119,"level":75,"exp":1232064,"isSkill":true},"bounty_hunter":{"rank":-1,"score":-1,"isSkill":false},"bounty_hunter_rouges":{"rank":-1,"score":-1,"isSkill":false},"dominion_tower":{"rank":46648,"score":1466678,"isSkill":false},"crucible":{"rank":-1,"score":-1,"isSkill":false},"castle_wars":{"rank":-1,"score":-1,"isSkill":false},"BA_attackers":{"rank":20069,"score":2265,"isSkill":false},"BA_defenders":{"rank":72076,"score":792,"isSkill":false},"BA_collectors":{"rank":85844,"score":802,"isSkill":false},"BA_healers":{"rank":91093,"score":1086,"isSkill":false},"duel_tournaments":{"rank":-1,"score":-1,"isSkill":false},"mobilising_armies":{"rank":-1,"score":-1,"isSkill":false},"conquest":{"rank":19481,"score":1266,"isSkill":false},"fist_of_guthix":{"rank":-1,"score":-1,"isSkill":false},"GG_resource":{"rank":-1,"score":-1,"isSkill":false},"GG_athletics":{"rank":2003,"score":622,"isSkill":false},"we2":{"rank":-1,"score":-1,"isSkill":false},"heist_guard":{"rank":-1,"score":-1,"isSkill":false},"heist_robber":{"rank":-1,"score":-1,"isSkill":false},"CFP":{"rank":-1,"score":-1,"isSkill":false}}