[
  {
    "rsn": "Drumgun",
    "overall": {
      "rank": 23,
      "level": 2715,
      "exp": 5400000000
    },
    "attack": {
      "rank": 14,
      "level": 99,
      "exp": 200000000
    },
    "defence": {
      "rank": 11,
      "level": 99,
      "exp": 200000000
    },
    "strength": {
      "rank": 13,
      "level": 99,
      "exp": 200000000
    },
    "constitution": {
      "rank": 3,
      "level": 99,
      "exp": 200000000
    },
    "ranged": {
      "rank": 13,
      "level": 99,
      "exp": 200000000
    },
    "prayer": {
      "rank": 22,
      "level": 99,
      "exp": 200000000
    },
    "magic": {
      "rank": 1,
      "level": 99,
      "exp": 200000000
    },
    "cooking": {
      "rank": 23,
      "level": 99,
      "exp": 200000000
    },
    "woodcutting": {
      "rank": 71,
      "level": 99,
      "exp": 200000000
    },
    "fletching": {
      "rank": 41,
      "level": 99,
      "exp": 200000000
    },
    "fishing": {
      "rank": 28,
      "level": 99,
      "exp": 200000000
    },
    "firemaking": {
      "rank": 207,
      "level": 99,
      "exp": 200000000
    },
    "crafting": {
      "rank": 16,
      "level": 99,
      "exp": 200000000
    },
    "smithing": {
      "rank": 57,
      "level": 99,
      "exp": 200000000
    },
    "mining": {
      "rank": 37,
      "level": 99,
      "exp": 200000000
    },
    "herblore": {
      "rank": 47,
      "level": 99,
      "exp": 200000000
    },
    "agility": {
      "rank": 25,
      "level": 99,
      "exp": 200000000
    },
    "thieving": {
      "rank": 77,
      "level": 99,
      "exp": 200000000
    },
    "slayer": {
      "rank": 57,
      "level": 99,
      "exp": 200000000
    },
    "farming": {
      "rank": 97,
      "level": 99,
      "exp": 200000000
    },
    "runecrafting": {
      "rank": 15,
      "level": 99,
      "exp": 200000000
    },
    "hunter": {
      "rank": 5,
      "level": 99,
      "exp": 200000000
    },
    "construction": {
      "rank": 23,
      "level": 99,
      "exp": 200000000
    },
    "summoning": {
      "rank": 1,
      "level": 99,
      "exp": 200000000
    },
    "dungeoneering": {
      "rank": 1027,
      "level": 120,
      "exp": 200000000
    },
    "divination": {
      "rank": 1,
      "level": 99,
      "exp": 200000000
    },
    "invention": {
      "rank": 36,
      "level": 120,
      "exp": 200000000
    },
    "bounty_hunter": {
      "rank": -1,
      "score": -1
    },
    "bounty_hunter_rouges": {
      "rank": -1,
      "score": -1
    },
    "dominion_tower": {
      "rank": -1,
      "score": -1
    },
    "crucible": {
      "rank": -1,
      "score": -1
    },
    "castle_wars": {
      "rank": 96,
      "score": 7365
    },
    "BA_attackers": {
      "rank": 34933,
      "score": 1673
    },
    "BA_defenders": {
      "rank": -1,
      "score": -1
    },
    "BA_collectors": {
      "rank": 26483,
      "score": 1586
    },
    "BA_healers": {
      "rank": 53276,
      "score": 1578
    },
    "duel_tournaments": {
      "rank": -1,
      "score": -1
    },
    "mobilising_armies": {
      "rank": 12333,
      "score": 300
    },
    "conquest": {
      "rank": 3653,
      "score": 1519
    },
    "fist_of_guthix": {
      "rank": -1,
      "score": -1
    },
    "GG_resource": {
      "rank": -1,
      "score": -1
    },
    "GG_athletics": {
      "rank": -1,
      "score": -1
    },
    "we2": {
      "rank": -1,
      "score": -1
    },
    "heist_guard": {
      "rank": -1,
      "score": -1
    },
    "heist_robber": {
      "rank": -1,
      "score": -1
    },
    "CFP": {
      "rank": -1,
      "score": -1
    }
  },
  {
    "rsn": "Zezima",
    "overall": {
      "rank": 63,
      "level": 2715,
      "exp": 5400000000
    },
    "attack": {
      "rank": 559,
      "level": 99,
      "exp": 200000000
    },
    "defence": {
      "rank": 1099,
      "level": 99,
      "exp": 200000000
    },
    "strength": {
      "rank": 570,
      "level": 99,
      "exp": 200000000
    },
    "constitution": {
      "rank": 486,
      "level": 99,
      "exp": 200000000
    },
    "ranged": {
      "rank": 824,
      "level": 99,
      "exp": 200000000
    },
    "prayer": {
      "rank": 300,
      "level": 99,
      "exp": 200000000
    },
    "magic": {
      "rank": 733,
      "level": 99,
      "exp": 200000000
    },
    "cooking": {
      "rank": 3,
      "level": 99,
      "exp": 200000000
    },
    "woodcutting": {
      "rank": 243,
      "level": 99,
      "exp": 200000000
    },
    "fletching": {
      "rank": 99,
      "level": 99,
      "exp": 200000000
    },
    "fishing": {
      "rank": 547,
      "level": 99,
      "exp": 200000000
    },
    "firemaking": {
      "rank": 303,
      "level": 99,
      "exp": 200000000
    },
    "crafting": {
      "rank": 258,
      "level": 99,
      "exp": 200000000
    },
    "smithing": {
      "rank": 307,
      "level": 99,
      "exp": 200000000
    },
    "mining": {
      "rank": 514,
      "level": 99,
      "exp": 200000000
    },
    "herblore": {
      "rank": 427,
      "level": 99,
      "exp": 200000000
    },
    "agility": {
      "rank": 157,
      "level": 99,
      "exp": 200000000
    },
    "thieving": {
      "rank": 5,
      "level": 99,
      "exp": 200000000
    },
    "slayer": {
      "rank": 480,
      "level": 99,
      "exp": 200000000
    },
    "farming": {
      "rank": 425,
      "level": 99,
      "exp": 200000000
    },
    "runecrafting": {
      "rank": 220,
      "level": 99,
      "exp": 200000000
    },
    "hunter": {
      "rank": 243,
      "level": 99,
      "exp": 200000000
    },
    "construction": {
      "rank": 217,
      "level": 99,
      "exp": 200000000
    },
    "summoning": {
      "rank": 215,
      "level": 99,
      "exp": 200000000
    },
    "dungeoneering": {
      "rank": 778,
      "level": 120,
      "exp": 200000000
    },
    "divination": {
      "rank": 222,
      "level": 99,
      "exp": 200000000
    },
    "invention": {
      "rank": 205,
      "level": 120,
      "exp": 200000000
    },
    "bounty_hunter": {
      "rank": -1,
      "score": -1
    },
    "bounty_hunter_rouges": {
      "rank": -1,
      "score": -1
    },
    "dominion_tower": {
      "rank": 123,
      "score": 26087488
    },
    "crucible": {
      "rank": -1,
      "score": -1
    },
    "castle_wars": {
      "rank": -1,
      "score": -1
    },
    "BA_attackers": {
      "rank": 2739,
      "score": 4285
    },
    "BA_defenders": {
      "rank": 2590,
      "score": 4161
    },
    "BA_collectors": {
      "rank": 1869,
      "score": 4354
    },
    "BA_healers": {
      "rank": 3423,
      "score": 4405
    },
    "duel_tournaments": {
      "rank": 1229,
      "score": 1944
    },
    "mobilising_armies": {
      "rank": 469,
      "score": 552
    },
    "conquest": {
      "rank": 22951,
      "score": 1258
    },
    "fist_of_guthix": {
      "rank": -1,
      "score": -1
    },
    "GG_resource": {
      "rank": 6914,
      "score": 631
    },
    "GG_athletics": {
      "rank": 22591,
      "score": 605
    },
    "we2": {
      "rank": -1,
      "score": -1
    },
    "heist_guard": {
      "rank": -1,
      "score": -1
    },
    "heist_robber": {
      "rank": -1,
      "score": -1
    },
    "CFP": {
      "rank": 12467,
      "score": 107
    }
  },
  {
    "rsn": "S_U_O_M_I",
    "overall": {
      "rank": 0,
      "level": 0,
      "exp": 0
    },
    "attack": {
      "rank": 0,
      "level": 0,
      "exp": 0
    },
    "defence": {
      "rank": 0,
      "level": 0,
      "exp": 0
    },
    "strength": {
      "rank": 0,
      "level": 0,
      "exp": 0
    },
    "constitution": {
      "rank": 0,
      "level": 0,
      "exp": 0
    },
    "ranged": {
      "rank": 0,
      "level": 0,
      "exp": 0
    },
    "prayer": {
      "rank": 0,
      "level": 0,
      "exp": 0
    },
    "magic": {
      "rank": 0,
      "level": 0,
      "exp": 0
    },
    "cooking": {
      "rank": 0,
      "level": 0,
      "exp": 0
    },
    "woodcutting": {
      "rank": 0,
      "level": 0,
      "exp": 0
    },
    "fletching": {
      "rank": 0,
      "level": 0,
      "exp": 0
    },
    "fishing": {
      "rank": 0,
      "level": 0,
      "exp": 0
    },
    "firemaking": {
      "rank": 0,
      "level": 0,
      "exp": 0
    },
    "crafting": {
      "rank": 0,
      "level": 0,
      "exp": 0
    },
    "smithing": {
      "rank": 0,
      "level": 0,
      "exp": 0
    },
    "mining": {
      "rank": 0,
      "level": 0,
      "exp": 0
    },
    "herblore": {
      "rank": 0,
      "level": 0,
      "exp": 0
    },
    "agility": {
      "rank": 0,
      "level": 0,
      "exp": 0
    },
    "thieving": {
      "rank": 0,
      "level": 0,
      "exp": 0
    },
    "slayer": {
      "rank": 0,
      "level": 0,
      "exp": 0
    },
    "farming": {
      "rank": 0,
      "level": 0,
      "exp": 0
    },
    "runecrafting": {
      "rank": 0,
      "level": 0,
      "exp": 0
    },
    "hunter": {
      "rank": 0,
      "level": 0,
      "exp": 0
    },
    "construction": {
      "rank": 0,
      "level": 0,
      "exp": 0
    },
    "summoning": {
      "rank": 0,
      "level": 0,
      "exp": 0
    },
    "dungeoneering": {
      "rank": 0,
      "level": 0,
      "exp": 0
    },
    "divination": {
      "rank": 0,
      "level": 0,
      "exp": 0
    },
    "invention": {
      "rank": 0,
      "level": 0,
      "exp": 0
    },
    "bounty_hunter": {
      "rank": 0,
      "score": 0
    },
    "bounty_hunter_rouges": {
      "rank": 0,
      "score": 0
    },
    "dominion_tower": {
      "rank": 0,
      "score": 0
    },
    "crucible": {
      "rank": 0,
      "score": 0
    },
    "castle_wars": {
      "rank": 0,
      "score": 0
    },
    "BA_attackers": {
      "rank": 0,
      "score": 0
    },
    "BA_defenders": {
      "rank": 0,
      "score": 0
    },
    "BA_collectors": {
      "rank": 0,
      "score": 0
    },
    "BA_healers": {
      "rank": 0,
      "score": 0
    },
    "duel_tournaments": {
      "rank": 0,
      "score": 0
    },
    "mobilising_armies": {
      "rank": 0,
      "score": 0
    },
    "conquest": {
      "rank": 0,
      "score": 0
    },
    "fist_of_guthix": {
      "rank": 0,
      "score": 0
    },
    "GG_resource": {
      "rank": 0,
      "score": 0
    },
    "GG_athletics": {
      "rank": 0,
      "score": 0
    },
    "we2": {
      "rank": 0,
      "score": 0
    },
    "heist_guard": {
      "rank": 0,
      "score": 0
    },
    "heist_robber": {
      "rank": 0,
      "score": 0
    },
    "CFP": {
      "rank": 0,
      "score": 0
    }
  },
  {
    "rsn": "Jake",
    "overall": {
      "rank": 55478,
      "level": 2596,
      "exp": 4924277732
    },
    "attack": {
      "rank": 13,
      "level": 99,
      "exp": 200000000
    },
    "defence": {
      "rank": 19,
      "level": 99,
      "exp": 200000000
    },
    "strength": {
      "rank": 24,
      "level": 99,
      "exp": 200000000
    },
    "constitution": {
      "rank": 6,
      "level": 99,
      "exp": 200000000
    },
    "ranged": {
      "rank": 18,
      "level": 99,
      "exp": 200000000
    },
    "prayer": {
      "rank": 23,
      "level": 99,
      "exp": 200000000
    },
    "magic": {
      "rank": 7,
      "level": 99,
      "exp": 200000000
    },
    "cooking": {
      "rank": 120,
      "level": 99,
      "exp": 200000000
    },
    "woodcutting": {
      "rank": 45,
      "level": 99,
      "exp": 200000000
    },
    "fletching": {
      "rank": 51,
      "level": 99,
      "exp": 200000000
    },
    "fishing": {
      "rank": 81,
      "level": 99,
      "exp": 200000000
    },
    "firemaking": {
      "rank": 53,
      "level": 99,
      "exp": 200000000
    },
    "crafting": {
      "rank": 22,
      "level": 99,
      "exp": 200000000
    },
    "smithing": {
      "rank": 78,
      "level": 99,
      "exp": 200000000
    },
    "mining": {
      "rank": 70,
      "level": 99,
      "exp": 200000000
    },
    "herblore": {
      "rank": 28,
      "level": 99,
      "exp": 200000000
    },
    "agility": {
      "rank": 1786,
      "level": 99,
      "exp": 65458472
    },
    "thieving": {
      "rank": 19,
      "level": 99,
      "exp": 200000000
    },
    "slayer": {
      "rank": 2,
      "level": 99,
      "exp": 200000000
    },
    "farming": {
      "rank": 42,
      "level": 99,
      "exp": 200000000
    },
    "runecrafting": {
      "rank": 1486,
      "level": 99,
      "exp": 58819260
    },
    "hunter": {
      "rank": 17,
      "level": 99,
      "exp": 200000000
    },
    "construction": {
      "rank": 25,
      "level": 99,
      "exp": 200000000
    },
    "summoning": {
      "rank": 3,
      "level": 99,
      "exp": 200000000
    },
    "dungeoneering": {
      "rank": 77,
      "level": 120,
      "exp": 200000000
    },
    "divination": {
      "rank": 51,
      "level": 99,
      "exp": 200000000
    },
    "invention": {
      "rank": -1,
      "level": 0,
      "exp": -1
    },
    "bounty_hunter": {
      "rank": -1,
      "score": -1
    },
    "bounty_hunter_rouges": {
      "rank": -1,
      "score": -1
    },
    "dominion_tower": {
      "rank": 28712,
      "score": 3161189
    },
    "crucible": {
      "rank": -1,
      "score": -1
    },
    "castle_wars": {
      "rank": 5748,
      "score": 790
    },
    "BA_attackers": {
      "rank": 75616,
      "score": 933
    },
    "BA_defenders": {
      "rank": 82111,
      "score": 659
    },
    "BA_collectors": {
      "rank": 20640,
      "score": 1853
    },
    "BA_healers": {
      "rank": 100846,
      "score": 857
    },
    "duel_tournaments": {
      "rank": 1930,
      "score": 1917
    },
    "mobilising_armies": {
      "rank": -1,
      "score": -1
    },
    "conquest": {
      "rank": 2440,
      "score": 1624
    },
    "fist_of_guthix": {
      "rank": 39615,
      "score": 2311
    },
    "GG_resource": {
      "rank": 772,
      "score": 720
    },
    "GG_athletics": {
      "rank": 22327,
      "score": 605
    },
    "we2": {
      "rank": -1,
      "score": -1
    },
    "heist_guard": {
      "rank": -1,
      "score": -1
    },
    "heist_robber": {
      "rank": -1,
      "score": -1
    },
    "CFP": {
      "rank": -1,
      "score": -1
    }
  },
  {
    "rsn": "Simon",
    "overall": {
      "rank": 147,
      "level": 2715,
      "exp": 4742691863
    },
    "attack": {
      "rank": 3067,
      "level": 99,
      "exp": 105531345
    },
    "defence": {
      "rank": 727,
      "level": 99,
      "exp": 200000000
    },
    "strength": {
      "rank": 944,
      "level": 99,
      "exp": 172759494
    },
    "constitution": {
      "rank": 414,
      "level": 99,
      "exp": 200000000
    },
    "ranged": {
      "rank": 9,
      "level": 99,
      "exp": 200000000
    },
    "prayer": {
      "rank": 19,
      "level": 99,
      "exp": 200000000
    },
    "magic": {
      "rank": 643,
      "level": 99,
      "exp": 200000000
    },
    "cooking": {
      "rank": 597,
      "level": 99,
      "exp": 200000000
    },
    "woodcutting": {
      "rank": 79,
      "level": 99,
      "exp": 200000000
    },
    "fletching": {
      "rank": 82,
      "level": 99,
      "exp": 200000000
    },
    "fishing": {
      "rank": 1199,
      "level": 99,
      "exp": 157445648
    },
    "firemaking": {
      "rank": 455,
      "level": 99,
      "exp": 200000000
    },
    "crafting": {
      "rank": 159,
      "level": 99,
      "exp": 200000000
    },
    "smithing": {
      "rank": 237,
      "level": 99,
      "exp": 200000000
    },
    "mining": {
      "rank": 78,
      "level": 99,
      "exp": 200000000
    },
    "herblore": {
      "rank": 306,
      "level": 99,
      "exp": 200000000
    },
    "agility": {
      "rank": 345,
      "level": 99,
      "exp": 169244363
    },
    "thieving": {
      "rank": 6388,
      "level": 99,
      "exp": 105438999
    },
    "slayer": {
      "rank": 1064,
      "level": 99,
      "exp": 172307039
    },
    "farming": {
      "rank": 16,
      "level": 99,
      "exp": 200000000
    },
    "runecrafting": {
      "rank": 439,
      "level": 99,
      "exp": 129018726
    },
    "hunter": {
      "rank": 591,
      "level": 99,
      "exp": 110435296
    },
    "construction": {
      "rank": 1,
      "level": 99,
      "exp": 200000000
    },
    "summoning": {
      "rank": 579,
      "level": 99,
      "exp": 200000000
    },
    "dungeoneering": {
      "rank": 452,
      "level": 120,
      "exp": 200000000
    },
    "divination": {
      "rank": 1186,
      "level": 99,
      "exp": 85876857
    },
    "invention": {
      "rank": 2731,
      "level": 120,
      "exp": 134634096
    },
    "bounty_hunter": {
      "rank": -1,
      "score": -1
    },
    "bounty_hunter_rouges": {
      "rank": -1,
      "score": -1
    },
    "dominion_tower": {
      "rank": 7233,
      "score": 5302465
    },
    "crucible": {
      "rank": -1,
      "score": -1
    },
    "castle_wars": {
      "rank": -1,
      "score": -1
    },
    "BA_attackers": {
      "rank": 39199,
      "score": 1550
    },
    "BA_defenders": {
      "rank": 24770,
      "score": 1533
    },
    "BA_collectors": {
      "rank": 28021,
      "score": 1538
    },
    "BA_healers": {
      "rank": 53565,
      "score": 1571
    },
    "duel_tournaments": {
      "rank": -1,
      "score": -1
    },
    "mobilising_armies": {
      "rank": 3456,
      "score": 401
    },
    "conquest": {
      "rank": 15528,
      "score": 1268
    },
    "fist_of_guthix": {
      "rank": -1,
      "score": -1
    },
    "GG_resource": {
      "rank": 20807,
      "score": 440
    },
    "GG_athletics": {
      "rank": 7666,
      "score": 617
    },
    "we2": {
      "rank": 10356,
      "score": 15
    },
    "heist_guard": {
      "rank": -1,
      "score": -1
    },
    "heist_robber": {
      "rank": -1,
      "score": -1
    },
    "CFP": {
      "rank": 27741,
      "score": 79
    }
  },
  {
    "rsn": "Kingduffy",
    "overall": {
      "rank": 108,
      "level": 2715,
      "exp": 5195510368
    },
    "attack": {
      "rank": 1039,
      "level": 99,
      "exp": 166823292
    },
    "defence": {
      "rank": 1582,
      "level": 99,
      "exp": 199943606
    },
    "strength": {
      "rank": 973,
      "level": 99,
      "exp": 168610579
    },
    "constitution": {
      "rank": 549,
      "level": 99,
      "exp": 200000000
    },
    "ranged": {
      "rank": 1668,
      "level": 99,
      "exp": 191585898
    },
    "prayer": {
      "rank": 180,
      "level": 99,
      "exp": 200000000
    },
    "magic": {
      "rank": 1704,
      "level": 99,
      "exp": 199455408
    },
    "cooking": {
      "rank": 7,
      "level": 99,
      "exp": 200000000
    },
    "woodcutting": {
      "rank": 488,
      "level": 99,
      "exp": 192795211
    },
    "fletching": {
      "rank": 34,
      "level": 99,
      "exp": 200000000
    },
    "fishing": {
      "rank": 912,
      "level": 99,
      "exp": 200000000
    },
    "firemaking": {
      "rank": 631,
      "level": 99,
      "exp": 200000000
    },
    "crafting": {
      "rank": 302,
      "level": 99,
      "exp": 200000000
    },
    "smithing": {
      "rank": 392,
      "level": 99,
      "exp": 199502043
    },
    "mining": {
      "rank": 967,
      "level": 99,
      "exp": 183351489
    },
    "herblore": {
      "rank": 598,
      "level": 99,
      "exp": 199631378
    },
    "agility": {
      "rank": 362,
      "level": 99,
      "exp": 163152564
    },
    "thieving": {
      "rank": 2094,
      "level": 99,
      "exp": 200000000
    },
    "slayer": {
      "rank": 692,
      "level": 99,
      "exp": 200000000
    },
    "farming": {
      "rank": 228,
      "level": 99,
      "exp": 200000000
    },
    "runecrafting": {
      "rank": 298,
      "level": 99,
      "exp": 165735058
    },
    "hunter": {
      "rank": 295,
      "level": 99,
      "exp": 200000000
    },
    "construction": {
      "rank": 281,
      "level": 99,
      "exp": 200000000
    },
    "summoning": {
      "rank": 1195,
      "level": 99,
      "exp": 199946320
    },
    "dungeoneering": {
      "rank": 1106,
      "level": 120,
      "exp": 200000000
    },
    "divination": {
      "rank": 312,
      "level": 99,
      "exp": 168163721
    },
    "invention": {
      "rank": 1153,
      "level": 120,
      "exp": 196813801
    },
    "bounty_hunter": {
      "rank": -1,
      "score": -1
    },
    "bounty_hunter_rouges": {
      "rank": 7388,
      "score": 1818
    },
    "dominion_tower": {
      "rank": 47616,
      "score": 1901220
    },
    "crucible": {
      "rank": -1,
      "score": -1
    },
    "castle_wars": {
      "rank": -1,
      "score": -1
    },
    "BA_attackers": {
      "rank": 26079,
      "score": 1981
    },
    "BA_defenders": {
      "rank": 90213,
      "score": 593
    },
    "BA_collectors": {
      "rank": 98353,
      "score": 672
    },
    "BA_healers": {
      "rank": 145435,
      "score": 571
    },
    "duel_tournaments": {
      "rank": -1,
      "score": -1
    },
    "mobilising_armies": {
      "rank": 1881,
      "score": 413
    },
    "conquest": {
      "rank": 15944,
      "score": 1267
    },
    "fist_of_guthix": {
      "rank": 137578,
      "score": 785
    },
    "GG_resource": {
      "rank": -1,
      "score": -1
    },
    "GG_athletics": {
      "rank": 92510,
      "score": 544
    },
    "we2": {
      "rank": -1,
      "score": -1
    },
    "heist_guard": {
      "rank": -1,
      "score": -1
    },
    "heist_robber": {
      "rank": -1,
      "score": -1
    },
    "CFP": {
      "rank": 100133,
      "score": 11
    }
  },
  {
    "rsn": "Rip_Bector",
    "overall": {
      "rank": 0,
      "level": 0,
      "exp": 0
    },
    "attack": {
      "rank": 0,
      "level": 0,
      "exp": 0
    },
    "defence": {
      "rank": 0,
      "level": 0,
      "exp": 0
    },
    "strength": {
      "rank": 0,
      "level": 0,
      "exp": 0
    },
    "constitution": {
      "rank": 0,
      "level": 0,
      "exp": 0
    },
    "ranged": {
      "rank": 0,
      "level": 0,
      "exp": 0
    },
    "prayer": {
      "rank": 0,
      "level": 0,
      "exp": 0
    },
    "magic": {
      "rank": 0,
      "level": 0,
      "exp": 0
    },
    "cooking": {
      "rank": 0,
      "level": 0,
      "exp": 0
    },
    "woodcutting": {
      "rank": 0,
      "level": 0,
      "exp": 0
    },
    "fletching": {
      "rank": 0,
      "level": 0,
      "exp": 0
    },
    "fishing": {
      "rank": 0,
      "level": 0,
      "exp": 0
    },
    "firemaking": {
      "rank": 0,
      "level": 0,
      "exp": 0
    },
    "crafting": {
      "rank": 0,
      "level": 0,
      "exp": 0
    },
    "smithing": {
      "rank": 0,
      "level": 0,
      "exp": 0
    },
    "mining": {
      "rank": 0,
      "level": 0,
      "exp": 0
    },
    "herblore": {
      "rank": 0,
      "level": 0,
      "exp": 0
    },
    "agility": {
      "rank": 0,
      "level": 0,
      "exp": 0
    },
    "thieving": {
      "rank": 0,
      "level": 0,
      "exp": 0
    },
    "slayer": {
      "rank": 0,
      "level": 0,
      "exp": 0
    },
    "farming": {
      "rank": 0,
      "level": 0,
      "exp": 0
    },
    "runecrafting": {
      "rank": 0,
      "level": 0,
      "exp": 0
    },
    "hunter": {
      "rank": 0,
      "level": 0,
      "exp": 0
    },
    "construction": {
      "rank": 0,
      "level": 0,
      "exp": 0
    },
    "summoning": {
      "rank": 0,
      "level": 0,
      "exp": 0
    },
    "dungeoneering": {
      "rank": 0,
      "level": 0,
      "exp": 0
    },
    "divination": {
      "rank": 0,
      "level": 0,
      "exp": 0
    },
    "invention": {
      "rank": 0,
      "level": 0,
      "exp": 0
    },
    "bounty_hunter": {
      "rank": 0,
      "score": 0
    },
    "bounty_hunter_rouges": {
      "rank": 0,
      "score": 0
    },
    "dominion_tower": {
      "rank": 0,
      "score": 0
    },
    "crucible": {
      "rank": 0,
      "score": 0
    },
    "castle_wars": {
      "rank": 0,
      "score": 0
    },
    "BA_attackers": {
      "rank": 0,
      "score": 0
    },
    "BA_defenders": {
      "rank": 0,
      "score": 0
    },
    "BA_collectors": {
      "rank": 0,
      "score": 0
    },
    "BA_healers": {
      "rank": 0,
      "score": 0
    },
    "duel_tournaments": {
      "rank": 0,
      "score": 0
    },
    "mobilising_armies": {
      "rank": 0,
      "score": 0
    },
    "conquest": {
      "rank": 0,
      "score": 0
    },
    "fist_of_guthix": {
      "rank": 0,
      "score": 0
    },
    "GG_resource": {
      "rank": 0,
      "score": 0
    },
    "GG_athletics": {
      "rank": 0,
      "score": 0
    },
    "we2": {
      "rank": 0,
      "score": 0
    },
    "heist_guard": {
      "rank": 0,
      "score": 0
    },
    "heist_robber": {
      "rank": 0,
      "score": 0
    },
    "CFP": {
      "rank": 0,
      "score": 0
    }
  },
  {
    "rsn": "Zarfot",
    "overall": {
      "rank": 0,
      "level": 0,
      "exp": 0
    },
    "attack": {
      "rank": 0,
      "level": 0,
      "exp": 0
    },
    "defence": {
      "rank": 0,
      "level": 0,
      "exp": 0
    },
    "strength": {
      "rank": 0,
      "level": 0,
      "exp": 0
    },
    "constitution": {
      "rank": 0,
      "level": 0,
      "exp": 0
    },
    "ranged": {
      "rank": 0,
      "level": 0,
      "exp": 0
    },
    "prayer": {
      "rank": 0,
      "level": 0,
      "exp": 0
    },
    "magic": {
      "rank": 0,
      "level": 0,
      "exp": 0
    },
    "cooking": {
      "rank": 0,
      "level": 0,
      "exp": 0
    },
    "woodcutting": {
      "rank": 0,
      "level": 0,
      "exp": 0
    },
    "fletching": {
      "rank": 0,
      "level": 0,
      "exp": 0
    },
    "fishing": {
      "rank": 0,
      "level": 0,
      "exp": 0
    },
    "firemaking": {
      "rank": 0,
      "level": 0,
      "exp": 0
    },
    "crafting": {
      "rank": 0,
      "level": 0,
      "exp": 0
    },
    "smithing": {
      "rank": 0,
      "level": 0,
      "exp": 0
    },
    "mining": {
      "rank": 0,
      "level": 0,
      "exp": 0
    },
    "herblore": {
      "rank": 0,
      "level": 0,
      "exp": 0
    },
    "agility": {
      "rank": 0,
      "level": 0,
      "exp": 0
    },
    "thieving": {
      "rank": 0,
      "level": 0,
      "exp": 0
    },
    "slayer": {
      "rank": 0,
      "level": 0,
      "exp": 0
    },
    "farming": {
      "rank": 0,
      "level": 0,
      "exp": 0
    },
    "runecrafting": {
      "rank": 0,
      "level": 0,
      "exp": 0
    },
    "hunter": {
      "rank": 0,
      "level": 0,
      "exp": 0
    },
    "construction": {
      "rank": 0,
      "level": 0,
      "exp": 0
    },
    "summoning": {
      "rank": 0,
      "level": 0,
      "exp": 0
    },
    "dungeoneering": {
      "rank": 0,
      "level": 0,
      "exp": 0
    },
    "divination": {
      "rank": 0,
      "level": 0,
      "exp": 0
    },
    "invention": {
      "rank": 0,
      "level": 0,
      "exp": 0
    },
    "bounty_hunter": {
      "rank": 0,
      "score": 0
    },
    "bounty_hunter_rouges": {
      "rank": 0,
      "score": 0
    },
    "dominion_tower": {
      "rank": 0,
      "score": 0
    },
    "crucible": {
      "rank": 0,
      "score": 0
    },
    "castle_wars": {
      "rank": 0,
      "score": 0
    },
    "BA_attackers": {
      "rank": 0,
      "score": 0
    },
    "BA_defenders": {
      "rank": 0,
      "score": 0
    },
    "BA_collectors": {
      "rank": 0,
      "score": 0
    },
    "BA_healers": {
      "rank": 0,
      "score": 0
    },
    "duel_tournaments": {
      "rank": 0,
      "score": 0
    },
    "mobilising_armies": {
      "rank": 0,
      "score": 0
    },
    "conquest": {
      "rank": 0,
      "score": 0
    },
    "fist_of_guthix": {
      "rank": 0,
      "score": 0
    },
    "GG_resource": {
      "rank": 0,
      "score": 0
    },
    "GG_athletics": {
      "rank": 0,
      "score": 0
    },
    "we2": {
      "rank": 0,
      "score": 0
    },
    "heist_guard": {
      "rank": 0,
      "score": 0
    },
    "heist_robber": {
      "rank": 0,
      "score": 0
    },
    "CFP": {
      "rank": 0,
      "score": 0
    }
  },
  {
    "rsn": "Supersongoko",
    "overall": {
      "rank": 1498,
      "level": 2715,
      "exp": 2392877325
    },
    "attack": {
      "rank": 13724,
      "level": 99,
      "exp": 50939389
    },
    "defence": {
      "rank": 21412,
      "level": 99,
      "exp": 50425394
    },
    "strength": {
      "rank": 13905,
      "level": 99,
      "exp": 51010891
    },
    "constitution": {
      "rank": 11727,
      "level": 99,
      "exp": 97580849
    },
    "ranged": {
      "rank": 10908,
      "level": 99,
      "exp": 83799641
    },
    "prayer": {
      "rank": 1121,
      "level": 99,
      "exp": 107496520
    },
    "magic": {
      "rank": 10748,
      "level": 99,
      "exp": 88181178
    },
    "cooking": {
      "rank": 191,
      "level": 99,
      "exp": 200000000
    },
    "woodcutting": {
      "rank": 2459,
      "level": 99,
      "exp": 72349867
    },
    "fletching": {
      "rank": 1320,
      "level": 99,
      "exp": 105781358
    },
    "fishing": {
      "rank": 4151,
      "level": 99,
      "exp": 92809754
    },
    "firemaking": {
      "rank": 1055,
      "level": 99,
      "exp": 200000000
    },
    "crafting": {
      "rank": 2998,
      "level": 99,
      "exp": 43399254
    },
    "smithing": {
      "rank": 4409,
      "level": 99,
      "exp": 41658738
    },
    "mining": {
      "rank": 8280,
      "level": 99,
      "exp": 44629182
    },
    "herblore": {
      "rank": 3735,
      "level": 99,
      "exp": 60403078
    },
    "agility": {
      "rank": 2271,
      "level": 99,
      "exp": 53688281
    },
    "thieving": {
      "rank": 3461,
      "level": 99,
      "exp": 131080426
    },
    "slayer": {
      "rank": 10044,
      "level": 99,
      "exp": 54554024
    },
    "farming": {
      "rank": 881,
      "level": 99,
      "exp": 133702444
    },
    "runecrafting": {
      "rank": 2712,
      "level": 99,
      "exp": 38019340
    },
    "hunter": {
      "rank": 2675,
      "level": 99,
      "exp": 40658826
    },
    "construction": {
      "rank": 2176,
      "level": 99,
      "exp": 44188562
    },
    "summoning": {
      "rank": 2169,
      "level": 99,
      "exp": 112335029
    },
    "dungeoneering": {
      "rank": 53,
      "level": 120,
      "exp": 200000000
    },
    "divination": {
      "rank": 2419,
      "level": 99,
      "exp": 44564560
    },
    "invention": {
      "rank": 2111,
      "level": 120,
      "exp": 149620740
    },
    "bounty_hunter": {
      "rank": -1,
      "score": -1
    },
    "bounty_hunter_rouges": {
      "rank": -1,
      "score": -1
    },
    "dominion_tower": {
      "rank": 13589,
      "score": 4411777
    },
    "crucible": {
      "rank": -1,
      "score": -1
    },
    "castle_wars": {
      "rank": -1,
      "score": -1
    },
    "BA_attackers": {
      "rank": 136297,
      "score": 552
    },
    "BA_defenders": {
      "rank": 70871,
      "score": 746
    },
    "BA_collectors": {
      "rank": -1,
      "score": -1
    },
    "BA_healers": {
      "rank": -1,
      "score": -1
    },
    "duel_tournaments": {
      "rank": 4092,
      "score": 1864
    },
    "mobilising_armies": {
      "rank": -1,
      "score": -1
    },
    "conquest": {
      "rank": -1,
      "score": -1
    },
    "fist_of_guthix": {
      "rank": -1,
      "score": -1
    },
    "GG_resource": {
      "rank": 44718,
      "score": 286
    },
    "GG_athletics": {
      "rank": 76131,
      "score": 550
    },
    "we2": {
      "rank": -1,
      "score": -1
    },
    "heist_guard": {
      "rank": -1,
      "score": -1
    },
    "heist_robber": {
      "rank": -1,
      "score": -1
    },
    "CFP": {
      "rank": 3967,
      "score": 133
    }
  },
  {
    "rsn": "Sael",
    "overall": {
      "rank": 60167,
      "level": 2589,
      "exp": 506823176
    },
    "attack": {
      "rank": 69865,
      "level": 99,
      "exp": 18821515
    },
    "defence": {
      "rank": 76815,
      "level": 99,
      "exp": 18861452
    },
    "strength": {
      "rank": 54401,
      "level": 99,
      "exp": 22665439
    },
    "constitution": {
      "rank": 72777,
      "level": 99,
      "exp": 31586590
    },
    "ranged": {
      "rank": 58438,
      "level": 99,
      "exp": 23353352
    },
    "prayer": {
      "rank": 56326,
      "level": 99,
      "exp": 14406117
    },
    "magic": {
      "rank": 57874,
      "level": 99,
      "exp": 22931026
    },
    "cooking": {
      "rank": 12173,
      "level": 99,
      "exp": 28069238
    },
    "woodcutting": {
      "rank": 57646,
      "level": 99,
      "exp": 15617588
    },
    "fletching": {
      "rank": 18275,
      "level": 99,
      "exp": 17450410
    },
    "fishing": {
      "rank": 77760,
      "level": 99,
      "exp": 14235370
    },
    "firemaking": {
      "rank": 33899,
      "level": 99,
      "exp": 18088244
    },
    "crafting": {
      "rank": 57325,
      "level": 99,
      "exp": 13929297
    },
    "smithing": {
      "rank": 38521,
      "level": 99,
      "exp": 15179461
    },
    "mining": {
      "rank": 44671,
      "level": 99,
      "exp": 15981294
    },
    "herblore": {
      "rank": 39825,
      "level": 99,
      "exp": 16088541
    },
    "agility": {
      "rank": 33207,
      "level": 99,
      "exp": 14808337
    },
    "thieving": {
      "rank": 18052,
      "level": 99,
      "exp": 34696698
    },
    "slayer": {
      "rank": 41755,
      "level": 99,
      "exp": 21059392
    },
    "farming": {
      "rank": 38952,
      "level": 99,
      "exp": 15920218
    },
    "runecrafting": {
      "rank": 60609,
      "level": 99,
      "exp": 13299483
    },
    "hunter": {
      "rank": 54386,
      "level": 99,
      "exp": 13534445
    },
    "construction": {
      "rank": 34051,
      "level": 99,
      "exp": 15295288
    },
    "summoning": {
      "rank": 39535,
      "level": 99,
      "exp": 14464317
    },
    "dungeoneering": {
      "rank": 43639,
      "level": 110,
      "exp": 41419827
    },
    "divination": {
      "rank": 26711,
      "level": 99,
      "exp": 15057209
    },
    "invention": {
      "rank": -1,
      "level": 0,
      "exp": -1
    },
    "bounty_hunter": {
      "rank": -1,
      "score": -1
    },
    "bounty_hunter_rouges": {
      "rank": -1,
      "score": -1
    },
    "dominion_tower": {
      "rank": 87433,
      "score": 321058
    },
    "crucible": {
      "rank": -1,
      "score": -1
    },
    "castle_wars": {
      "rank": -1,
      "score": -1
    },
    "BA_attackers": {
      "rank": 78375,
      "score": 905
    },
    "BA_defenders": {
      "rank": 74906,
      "score": 703
    },
    "BA_collectors": {
      "rank": 75687,
      "score": 799
    },
    "BA_healers": {
      "rank": 122495,
      "score": 706
    },
    "duel_tournaments": {
      "rank": -1,
      "score": -1
    },
    "mobilising_armies": {
      "rank": -1,
      "score": -1
    },
    "conquest": {
      "rank": -1,
      "score": -1
    },
    "fist_of_guthix": {
      "rank": 699,
      "score": 22321
    },
    "GG_resource": {
      "rank": 2165,
      "score": 700
    },
    "GG_athletics": {
      "rank": 1524,
      "score": 622
    },
    "we2": {
      "rank": -1,
      "score": -1
    },
    "heist_guard": {
      "rank": -1,
      "score": -1
    },
    "heist_robber": {
      "rank": -1,
      "score": -1
    },
    "CFP": {
      "rank": 17784,
      "score": 96
    }
  },
  {
    "rsn": "Eiwa",
    "overall": {
      "rank": 0,
      "level": 0,
      "exp": 0
    },
    "attack": {
      "rank": 0,
      "level": 0,
      "exp": 0
    },
    "defence": {
      "rank": 0,
      "level": 0,
      "exp": 0
    },
    "strength": {
      "rank": 0,
      "level": 0,
      "exp": 0
    },
    "constitution": {
      "rank": 0,
      "level": 0,
      "exp": 0
    },
    "ranged": {
      "rank": 0,
      "level": 0,
      "exp": 0
    },
    "prayer": {
      "rank": 0,
      "level": 0,
      "exp": 0
    },
    "magic": {
      "rank": 0,
      "level": 0,
      "exp": 0
    },
    "cooking": {
      "rank": 0,
      "level": 0,
      "exp": 0
    },
    "woodcutting": {
      "rank": 0,
      "level": 0,
      "exp": 0
    },
    "fletching": {
      "rank": 0,
      "level": 0,
      "exp": 0
    },
    "fishing": {
      "rank": 0,
      "level": 0,
      "exp": 0
    },
    "firemaking": {
      "rank": 0,
      "level": 0,
      "exp": 0
    },
    "crafting": {
      "rank": 0,
      "level": 0,
      "exp": 0
    },
    "smithing": {
      "rank": 0,
      "level": 0,
      "exp": 0
    },
    "mining": {
      "rank": 0,
      "level": 0,
      "exp": 0
    },
    "herblore": {
      "rank": 0,
      "level": 0,
      "exp": 0
    },
    "agility": {
      "rank": 0,
      "level": 0,
      "exp": 0
    },
    "thieving": {
      "rank": 0,
      "level": 0,
      "exp": 0
    },
    "slayer": {
      "rank": 0,
      "level": 0,
      "exp": 0
    },
    "farming": {
      "rank": 0,
      "level": 0,
      "exp": 0
    },
    "runecrafting": {
      "rank": 0,
      "level": 0,
      "exp": 0
    },
    "hunter": {
      "rank": 0,
      "level": 0,
      "exp": 0
    },
    "construction": {
      "rank": 0,
      "level": 0,
      "exp": 0
    },
    "summoning": {
      "rank": 0,
      "level": 0,
      "exp": 0
    },
    "dungeoneering": {
      "rank": 0,
      "level": 0,
      "exp": 0
    },
    "divination": {
      "rank": 0,
      "level": 0,
      "exp": 0
    },
    "invention": {
      "rank": 0,
      "level": 0,
      "exp": 0
    },
    "bounty_hunter": {
      "rank": 0,
      "score": 0
    },
    "bounty_hunter_rouges": {
      "rank": 0,
      "score": 0
    },
    "dominion_tower": {
      "rank": 0,
      "score": 0
    },
    "crucible": {
      "rank": 0,
      "score": 0
    },
    "castle_wars": {
      "rank": 0,
      "score": 0
    },
    "BA_attackers": {
      "rank": 0,
      "score": 0
    },
    "BA_defenders": {
      "rank": 0,
      "score": 0
    },
    "BA_collectors": {
      "rank": 0,
      "score": 0
    },
    "BA_healers": {
      "rank": 0,
      "score": 0
    },
    "duel_tournaments": {
      "rank": 0,
      "score": 0
    },
    "mobilising_armies": {
      "rank": 0,
      "score": 0
    },
    "conquest": {
      "rank": 0,
      "score": 0
    },
    "fist_of_guthix": {
      "rank": 0,
      "score": 0
    },
    "GG_resource": {
      "rank": 0,
      "score": 0
    },
    "GG_athletics": {
      "rank": 0,
      "score": 0
    },
    "we2": {
      "rank": 0,
      "score": 0
    },
    "heist_guard": {
      "rank": 0,
      "score": 0
    },
    "heist_robber": {
      "rank": 0,
      "score": 0
    },
    "CFP": {
      "rank": 0,
      "score": 0
    }
  },
  {
    "rsn": "Broa",
    "overall": {
      "rank": 67583,
      "level": 2564,
      "exp": 381094337
    },
    "attack": {
      "rank": 157105,
      "level": 99,
      "exp": 13197963
    },
    "defence": {
      "rank": 23802,
      "level": 99,
      "exp": 45828234
    },
    "strength": {
      "rank": 109776,
      "level": 99,
      "exp": 15372292
    },
    "constitution": {
      "rank": 67238,
      "level": 99,
      "exp": 33242213
    },
    "ranged": {
      "rank": 131438,
      "level": 99,
      "exp": 14141200
    },
    "prayer": {
      "rank": 55285,
      "level": 99,
      "exp": 14445240
    },
    "magic": {
      "rank": 80313,
      "level": 99,
      "exp": 18519451
    },
    "cooking": {
      "rank": 129022,
      "level": 99,
      "exp": 13379946
    },
    "woodcutting": {
      "rank": 174125,
      "level": 96,
      "exp": 9936861
    },
    "fletching": {
      "rank": 112355,
      "level": 99,
      "exp": 13192576
    },
    "fishing": {
      "rank": 139539,
      "level": 94,
      "exp": 8159010
    },
    "firemaking": {
      "rank": 60691,
      "level": 99,
      "exp": 14829705
    },
    "crafting": {
      "rank": 92139,
      "level": 97,
      "exp": 11397454
    },
    "smithing": {
      "rank": 63444,
      "level": 99,
      "exp": 13606615
    },
    "mining": {
      "rank": 81762,
      "level": 99,
      "exp": 13377659
    },
    "herblore": {
      "rank": 105906,
      "level": 99,
      "exp": 13265191
    },
    "agility": {
      "rank": 118570,
      "level": 86,
      "exp": 3894492
    },
    "thieving": {
      "rank": 24150,
      "level": 99,
      "exp": 25711565
    },
    "slayer": {
      "rank": 27199,
      "level": 99,
      "exp": 27688722
    },
    "farming": {
      "rank": 95574,
      "level": 91,
      "exp": 6417977
    },
    "runecrafting": {
      "rank": 117504,
      "level": 88,
      "exp": 4540394
    },
    "hunter": {
      "rank": 109543,
      "level": 88,
      "exp": 4590790
    },
    "construction": {
      "rank": 113084,
      "level": 87,
      "exp": 4195754
    },
    "summoning": {
      "rank": 63803,
      "level": 99,
      "exp": 13617231
    },
    "dungeoneering": {
      "rank": 112431,
      "level": 95,
      "exp": 9443805
    },
    "divination": {
      "rank": 120601,
      "level": 82,
      "exp": 2634767
    },
    "invention": {
      "rank": 48343,
      "level": 76,
      "exp": 12467230
    },
    "bounty_hunter": {
      "rank": -1,
      "score": -1
    },
    "bounty_hunter_rouges": {
      "rank": -1,
      "score": -1
    },
    "dominion_tower": {
      "rank": 30931,
      "score": 2998191
    },
    "crucible": {
      "rank": -1,
      "score": -1
    },
    "castle_wars": {
      "rank": -1,
      "score": -1
    },
    "BA_attackers": {
      "rank": -1,
      "score": -1
    },
    "BA_defenders": {
      "rank": -1,
      "score": -1
    },
    "BA_collectors": {
      "rank": -1,
      "score": -1
    },
    "BA_healers": {
      "rank": -1,
      "score": -1
    },
    "duel_tournaments": {
      "rank": -1,
      "score": -1
    },
    "mobilising_armies": {
      "rank": -1,
      "score": -1
    },
    "conquest": {
      "rank": -1,
      "score": -1
    },
    "fist_of_guthix": {
      "rank": -1,
      "score": -1
    },
    "GG_resource": {
      "rank": 19480,
      "score": 450
    },
    "GG_athletics": {
      "rank": 97359,
      "score": 544
    },
    "we2": {
      "rank": -1,
      "score": -1
    },
    "heist_guard": {
      "rank": -1,
      "score": -1
    },
    "heist_robber": {
      "rank": -1,
      "score": -1
    },
    "CFP": {
      "rank": 5398,
      "score": 127
    }
  },
  {
    "rsn": "Asheka",
    "overall": {
      "rank": 0,
      "level": 0,
      "exp": 0
    },
    "attack": {
      "rank": 0,
      "level": 0,
      "exp": 0
    },
    "defence": {
      "rank": 0,
      "level": 0,
      "exp": 0
    },
    "strength": {
      "rank": 0,
      "level": 0,
      "exp": 0
    },
    "constitution": {
      "rank": 0,
      "level": 0,
      "exp": 0
    },
    "ranged": {
      "rank": 0,
      "level": 0,
      "exp": 0
    },
    "prayer": {
      "rank": 0,
      "level": 0,
      "exp": 0
    },
    "magic": {
      "rank": 0,
      "level": 0,
      "exp": 0
    },
    "cooking": {
      "rank": 0,
      "level": 0,
      "exp": 0
    },
    "woodcutting": {
      "rank": 0,
      "level": 0,
      "exp": 0
    },
    "fletching": {
      "rank": 0,
      "level": 0,
      "exp": 0
    },
    "fishing": {
      "rank": 0,
      "level": 0,
      "exp": 0
    },
    "firemaking": {
      "rank": 0,
      "level": 0,
      "exp": 0
    },
    "crafting": {
      "rank": 0,
      "level": 0,
      "exp": 0
    },
    "smithing": {
      "rank": 0,
      "level": 0,
      "exp": 0
    },
    "mining": {
      "rank": 0,
      "level": 0,
      "exp": 0
    },
    "herblore": {
      "rank": 0,
      "level": 0,
      "exp": 0
    },
    "agility": {
      "rank": 0,
      "level": 0,
      "exp": 0
    },
    "thieving": {
      "rank": 0,
      "level": 0,
      "exp": 0
    },
    "slayer": {
      "rank": 0,
      "level": 0,
      "exp": 0
    },
    "farming": {
      "rank": 0,
      "level": 0,
      "exp": 0
    },
    "runecrafting": {
      "rank": 0,
      "level": 0,
      "exp": 0
    },
    "hunter": {
      "rank": 0,
      "level": 0,
      "exp": 0
    },
    "construction": {
      "rank": 0,
      "level": 0,
      "exp": 0
    },
    "summoning": {
      "rank": 0,
      "level": 0,
      "exp": 0
    },
    "dungeoneering": {
      "rank": 0,
      "level": 0,
      "exp": 0
    },
    "divination": {
      "rank": 0,
      "level": 0,
      "exp": 0
    },
    "invention": {
      "rank": 0,
      "level": 0,
      "exp": 0
    },
    "bounty_hunter": {
      "rank": 0,
      "score": 0
    },
    "bounty_hunter_rouges": {
      "rank": 0,
      "score": 0
    },
    "dominion_tower": {
      "rank": 0,
      "score": 0
    },
    "crucible": {
      "rank": 0,
      "score": 0
    },
    "castle_wars": {
      "rank": 0,
      "score": 0
    },
    "BA_attackers": {
      "rank": 0,
      "score": 0
    },
    "BA_defenders": {
      "rank": 0,
      "score": 0
    },
    "BA_collectors": {
      "rank": 0,
      "score": 0
    },
    "BA_healers": {
      "rank": 0,
      "score": 0
    },
    "duel_tournaments": {
      "rank": 0,
      "score": 0
    },
    "mobilising_armies": {
      "rank": 0,
      "score": 0
    },
    "conquest": {
      "rank": 0,
      "score": 0
    },
    "fist_of_guthix": {
      "rank": 0,
      "score": 0
    },
    "GG_resource": {
      "rank": 0,
      "score": 0
    },
    "GG_athletics": {
      "rank": 0,
      "score": 0
    },
    "we2": {
      "rank": 0,
      "score": 0
    },
    "heist_guard": {
      "rank": 0,
      "score": 0
    },
    "heist_robber": {
      "rank": 0,
      "score": 0
    },
    "CFP": {
      "rank": 0,
      "score": 0
    }
  },
  {
    "rsn": "Akirahh",
    "overall": {
      "rank": 0,
      "level": 0,
      "exp": 0
    },
    "attack": {
      "rank": 0,
      "level": 0,
      "exp": 0
    },
    "defence": {
      "rank": 0,
      "level": 0,
      "exp": 0
    },
    "strength": {
      "rank": 0,
      "level": 0,
      "exp": 0
    },
    "constitution": {
      "rank": 0,
      "level": 0,
      "exp": 0
    },
    "ranged": {
      "rank": 0,
      "level": 0,
      "exp": 0
    },
    "prayer": {
      "rank": 0,
      "level": 0,
      "exp": 0
    },
    "magic": {
      "rank": 0,
      "level": 0,
      "exp": 0
    },
    "cooking": {
      "rank": 0,
      "level": 0,
      "exp": 0
    },
    "woodcutting": {
      "rank": 0,
      "level": 0,
      "exp": 0
    },
    "fletching": {
      "rank": 0,
      "level": 0,
      "exp": 0
    },
    "fishing": {
      "rank": 0,
      "level": 0,
      "exp": 0
    },
    "firemaking": {
      "rank": 0,
      "level": 0,
      "exp": 0
    },
    "crafting": {
      "rank": 0,
      "level": 0,
      "exp": 0
    },
    "smithing": {
      "rank": 0,
      "level": 0,
      "exp": 0
    },
    "mining": {
      "rank": 0,
      "level": 0,
      "exp": 0
    },
    "herblore": {
      "rank": 0,
      "level": 0,
      "exp": 0
    },
    "agility": {
      "rank": 0,
      "level": 0,
      "exp": 0
    },
    "thieving": {
      "rank": 0,
      "level": 0,
      "exp": 0
    },
    "slayer": {
      "rank": 0,
      "level": 0,
      "exp": 0
    },
    "farming": {
      "rank": 0,
      "level": 0,
      "exp": 0
    },
    "runecrafting": {
      "rank": 0,
      "level": 0,
      "exp": 0
    },
    "hunter": {
      "rank": 0,
      "level": 0,
      "exp": 0
    },
    "construction": {
      "rank": 0,
      "level": 0,
      "exp": 0
    },
    "summoning": {
      "rank": 0,
      "level": 0,
      "exp": 0
    },
    "dungeoneering": {
      "rank": 0,
      "level": 0,
      "exp": 0
    },
    "divination": {
      "rank": 0,
      "level": 0,
      "exp": 0
    },
    "invention": {
      "rank": 0,
      "level": 0,
      "exp": 0
    },
    "bounty_hunter": {
      "rank": 0,
      "score": 0
    },
    "bounty_hunter_rouges": {
      "rank": 0,
      "score": 0
    },
    "dominion_tower": {
      "rank": 0,
      "score": 0
    },
    "crucible": {
      "rank": 0,
      "score": 0
    },
    "castle_wars": {
      "rank": 0,
      "score": 0
    },
    "BA_attackers": {
      "rank": 0,
      "score": 0
    },
    "BA_defenders": {
      "rank": 0,
      "score": 0
    },
    "BA_collectors": {
      "rank": 0,
      "score": 0
    },
    "BA_healers": {
      "rank": 0,
      "score": 0
    },
    "duel_tournaments": {
      "rank": 0,
      "score": 0
    },
    "mobilising_armies": {
      "rank": 0,
      "score": 0
    },
    "conquest": {
      "rank": 0,
      "score": 0
    },
    "fist_of_guthix": {
      "rank": 0,
      "score": 0
    },
    "GG_resource": {
      "rank": 0,
      "score": 0
    },
    "GG_athletics": {
      "rank": 0,
      "score": 0
    },
    "we2": {
      "rank": 0,
      "score": 0
    },
    "heist_guard": {
      "rank": 0,
      "score": 0
    },
    "heist_robber": {
      "rank": 0,
      "score": 0
    },
    "CFP": {
      "rank": 0,
      "score": 0
    }
  },
  {
    "rsn": "PVM_WazZuP",
    "overall": {
      "rank": 0,
      "level": 0,
      "exp": 0
    },
    "attack": {
      "rank": 0,
      "level": 0,
      "exp": 0
    },
    "defence": {
      "rank": 0,
      "level": 0,
      "exp": 0
    },
    "strength": {
      "rank": 0,
      "level": 0,
      "exp": 0
    },
    "constitution": {
      "rank": 0,
      "level": 0,
      "exp": 0
    },
    "ranged": {
      "rank": 0,
      "level": 0,
      "exp": 0
    },
    "prayer": {
      "rank": 0,
      "level": 0,
      "exp": 0
    },
    "magic": {
      "rank": 0,
      "level": 0,
      "exp": 0
    },
    "cooking": {
      "rank": 0,
      "level": 0,
      "exp": 0
    },
    "woodcutting": {
      "rank": 0,
      "level": 0,
      "exp": 0
    },
    "fletching": {
      "rank": 0,
      "level": 0,
      "exp": 0
    },
    "fishing": {
      "rank": 0,
      "level": 0,
      "exp": 0
    },
    "firemaking": {
      "rank": 0,
      "level": 0,
      "exp": 0
    },
    "crafting": {
      "rank": 0,
      "level": 0,
      "exp": 0
    },
    "smithing": {
      "rank": 0,
      "level": 0,
      "exp": 0
    },
    "mining": {
      "rank": 0,
      "level": 0,
      "exp": 0
    },
    "herblore": {
      "rank": 0,
      "level": 0,
      "exp": 0
    },
    "agility": {
      "rank": 0,
      "level": 0,
      "exp": 0
    },
    "thieving": {
      "rank": 0,
      "level": 0,
      "exp": 0
    },
    "slayer": {
      "rank": 0,
      "level": 0,
      "exp": 0
    },
    "farming": {
      "rank": 0,
      "level": 0,
      "exp": 0
    },
    "runecrafting": {
      "rank": 0,
      "level": 0,
      "exp": 0
    },
    "hunter": {
      "rank": 0,
      "level": 0,
      "exp": 0
    },
    "construction": {
      "rank": 0,
      "level": 0,
      "exp": 0
    },
    "summoning": {
      "rank": 0,
      "level": 0,
      "exp": 0
    },
    "dungeoneering": {
      "rank": 0,
      "level": 0,
      "exp": 0
    },
    "divination": {
      "rank": 0,
      "level": 0,
      "exp": 0
    },
    "invention": {
      "rank": 0,
      "level": 0,
      "exp": 0
    },
    "bounty_hunter": {
      "rank": 0,
      "score": 0
    },
    "bounty_hunter_rouges": {
      "rank": 0,
      "score": 0
    },
    "dominion_tower": {
      "rank": 0,
      "score": 0
    },
    "crucible": {
      "rank": 0,
      "score": 0
    },
    "castle_wars": {
      "rank": 0,
      "score": 0
    },
    "BA_attackers": {
      "rank": 0,
      "score": 0
    },
    "BA_defenders": {
      "rank": 0,
      "score": 0
    },
    "BA_collectors": {
      "rank": 0,
      "score": 0
    },
    "BA_healers": {
      "rank": 0,
      "score": 0
    },
    "duel_tournaments": {
      "rank": 0,
      "score": 0
    },
    "mobilising_armies": {
      "rank": 0,
      "score": 0
    },
    "conquest": {
      "rank": 0,
      "score": 0
    },
    "fist_of_guthix": {
      "rank": 0,
      "score": 0
    },
    "GG_resource": {
      "rank": 0,
      "score": 0
    },
    "GG_athletics": {
      "rank": 0,
      "score": 0
    },
    "we2": {
      "rank": 0,
      "score": 0
    },
    "heist_guard": {
      "rank": 0,
      "score": 0
    },
    "heist_robber": {
      "rank": 0,
      "score": 0
    },
    "CFP": {
      "rank": 0,
      "score": 0
    }
  },
  {
    "rsn": "Articpine",
    "overall": {
      "rank": 0,
      "level": 0,
      "exp": 0
    },
    "attack": {
      "rank": 0,
      "level": 0,
      "exp": 0
    },
    "defence": {
      "rank": 0,
      "level": 0,
      "exp": 0
    },
    "strength": {
      "rank": 0,
      "level": 0,
      "exp": 0
    },
    "constitution": {
      "rank": 0,
      "level": 0,
      "exp": 0
    },
    "ranged": {
      "rank": 0,
      "level": 0,
      "exp": 0
    },
    "prayer": {
      "rank": 0,
      "level": 0,
      "exp": 0
    },
    "magic": {
      "rank": 0,
      "level": 0,
      "exp": 0
    },
    "cooking": {
      "rank": 0,
      "level": 0,
      "exp": 0
    },
    "woodcutting": {
      "rank": 0,
      "level": 0,
      "exp": 0
    },
    "fletching": {
      "rank": 0,
      "level": 0,
      "exp": 0
    },
    "fishing": {
      "rank": 0,
      "level": 0,
      "exp": 0
    },
    "firemaking": {
      "rank": 0,
      "level": 0,
      "exp": 0
    },
    "crafting": {
      "rank": 0,
      "level": 0,
      "exp": 0
    },
    "smithing": {
      "rank": 0,
      "level": 0,
      "exp": 0
    },
    "mining": {
      "rank": 0,
      "level": 0,
      "exp": 0
    },
    "herblore": {
      "rank": 0,
      "level": 0,
      "exp": 0
    },
    "agility": {
      "rank": 0,
      "level": 0,
      "exp": 0
    },
    "thieving": {
      "rank": 0,
      "level": 0,
      "exp": 0
    },
    "slayer": {
      "rank": 0,
      "level": 0,
      "exp": 0
    },
    "farming": {
      "rank": 0,
      "level": 0,
      "exp": 0
    },
    "runecrafting": {
      "rank": 0,
      "level": 0,
      "exp": 0
    },
    "hunter": {
      "rank": 0,
      "level": 0,
      "exp": 0
    },
    "construction": {
      "rank": 0,
      "level": 0,
      "exp": 0
    },
    "summoning": {
      "rank": 0,
      "level": 0,
      "exp": 0
    },
    "dungeoneering": {
      "rank": 0,
      "level": 0,
      "exp": 0
    },
    "divination": {
      "rank": 0,
      "level": 0,
      "exp": 0
    },
    "invention": {
      "rank": 0,
      "level": 0,
      "exp": 0
    },
    "bounty_hunter": {
      "rank": 0,
      "score": 0
    },
    "bounty_hunter_rouges": {
      "rank": 0,
      "score": 0
    },
    "dominion_tower": {
      "rank": 0,
      "score": 0
    },
    "crucible": {
      "rank": 0,
      "score": 0
    },
    "castle_wars": {
      "rank": 0,
      "score": 0
    },
    "BA_attackers": {
      "rank": 0,
      "score": 0
    },
    "BA_defenders": {
      "rank": 0,
      "score": 0
    },
    "BA_collectors": {
      "rank": 0,
      "score": 0
    },
    "BA_healers": {
      "rank": 0,
      "score": 0
    },
    "duel_tournaments": {
      "rank": 0,
      "score": 0
    },
    "mobilising_armies": {
      "rank": 0,
      "score": 0
    },
    "conquest": {
      "rank": 0,
      "score": 0
    },
    "fist_of_guthix": {
      "rank": 0,
      "score": 0
    },
    "GG_resource": {
      "rank": 0,
      "score": 0
    },
    "GG_athletics": {
      "rank": 0,
      "score": 0
    },
    "we2": {
      "rank": 0,
      "score": 0
    },
    "heist_guard": {
      "rank": 0,
      "score": 0
    },
    "heist_robber": {
      "rank": 0,
      "score": 0
    },
    "CFP": {
      "rank": 0,
      "score": 0
    }
  },
  {
    "rsn": "Eagledelt",
    "overall": {
      "rank": 107421,
      "level": 2414,
      "exp": 245074012
    },
    "attack": {
      "rank": 71919,
      "level": 99,
      "exp": 18490167
    },
    "defence": {
      "rank": 92112,
      "level": 99,
      "exp": 16793458
    },
    "strength": {
      "rank": 75885,
      "level": 99,
      "exp": 18635412
    },
    "constitution": {
      "rank": 103608,
      "level": 99,
      "exp": 24704310
    },
    "ranged": {
      "rank": 89703,
      "level": 99,
      "exp": 17465744
    },
    "prayer": {
      "rank": 80064,
      "level": 99,
      "exp": 13664109
    },
    "magic": {
      "rank": 84300,
      "level": 99,
      "exp": 17969654
    },
    "cooking": {
      "rank": 117727,
      "level": 99,
      "exp": 13514376
    },
    "woodcutting": {
      "rank": 92652,
      "level": 99,
      "exp": 14108984
    },
    "fletching": {
      "rank": 200128,
      "level": 90,
      "exp": 5694335
    },
    "fishing": {
      "rank": 89863,
      "level": 99,
      "exp": 13664098
    },
    "firemaking": {
      "rank": 81904,
      "level": 99,
      "exp": 13952199
    },
    "crafting": {
      "rank": 170000,
      "level": 83,
      "exp": 2752564
    },
    "smithing": {
      "rank": 192572,
      "level": 82,
      "exp": 2568771
    },
    "mining": {
      "rank": 117603,
      "level": 92,
      "exp": 7008014
    },
    "herblore": {
      "rank": 189307,
      "level": 89,
      "exp": 4914065
    },
    "agility": {
      "rank": 134527,
      "level": 84,
      "exp": 3003823
    },
    "thieving": {
      "rank": 137389,
      "level": 81,
      "exp": 2293049
    },
    "slayer": {
      "rank": 135882,
      "level": 95,
      "exp": 8892984
    },
    "farming": {
      "rank": 116719,
      "level": 86,
      "exp": 3838027
    },
    "runecrafting": {
      "rank": 161050,
      "level": 80,
      "exp": 2153175
    },
    "hunter": {
      "rank": 147181,
      "level": 81,
      "exp": 2392918
    },
    "construction": {
      "rank": 135282,
      "level": 83,
      "exp": 2903082
    },
    "summoning": {
      "rank": 186544,
      "level": 84,
      "exp": 3104659
    },
    "dungeoneering": {
      "rank": 126843,
      "level": 93,
      "exp": 7343608
    },
    "divination": {
      "rank": 143634,
      "level": 80,
      "exp": 2174726
    },
    "invention": {
      "rank": 91144,
      "level": 42,
      "exp": 1073701
    },
    "bounty_hunter": {
      "rank": -1,
      "score": -1
    },
    "bounty_hunter_rouges": {
      "rank": 43492,
      "score": 295
    },
    "dominion_tower": {
      "rank": -1,
      "score": -1
    },
    "crucible": {
      "rank": -1,
      "score": -1
    },
    "castle_wars": {
      "rank": -1,
      "score": -1
    },
    "BA_attackers": {
      "rank": 101400,
      "score": 736
    },
    "BA_defenders": {
      "rank": 74094,
      "score": 709
    },
    "BA_collectors": {
      "rank": 76495,
      "score": 793
    },
    "BA_healers": {
      "rank": 123058,
      "score": 703
    },
    "duel_tournaments": {
      "rank": -1,
      "score": -1
    },
    "mobilising_armies": {
      "rank": 7548,
      "score": 325
    },
    "conquest": {
      "rank": -1,
      "score": -1
    },
    "fist_of_guthix": {
      "rank": 50161,
      "score": 1949
    },
    "GG_resource": {
      "rank": -1,
      "score": -1
    },
    "GG_athletics": {
      "rank": -1,
      "score": -1
    },
    "we2": {
      "rank": -1,
      "score": -1
    },
    "heist_guard": {
      "rank": -1,
      "score": -1
    },
    "heist_robber": {
      "rank": -1,
      "score": -1
    },
    "CFP": {
      "rank": -1,
      "score": -1
    }
  },
  {
    "rsn": "Rui_Vieir2",
    "overall": {
      "rank": 0,
      "level": 0,
      "exp": 0
    },
    "attack": {
      "rank": 0,
      "level": 0,
      "exp": 0
    },
    "defence": {
      "rank": 0,
      "level": 0,
      "exp": 0
    },
    "strength": {
      "rank": 0,
      "level": 0,
      "exp": 0
    },
    "constitution": {
      "rank": 0,
      "level": 0,
      "exp": 0
    },
    "ranged": {
      "rank": 0,
      "level": 0,
      "exp": 0
    },
    "prayer": {
      "rank": 0,
      "level": 0,
      "exp": 0
    },
    "magic": {
      "rank": 0,
      "level": 0,
      "exp": 0
    },
    "cooking": {
      "rank": 0,
      "level": 0,
      "exp": 0
    },
    "woodcutting": {
      "rank": 0,
      "level": 0,
      "exp": 0
    },
    "fletching": {
      "rank": 0,
      "level": 0,
      "exp": 0
    },
    "fishing": {
      "rank": 0,
      "level": 0,
      "exp": 0
    },
    "firemaking": {
      "rank": 0,
      "level": 0,
      "exp": 0
    },
    "crafting": {
      "rank": 0,
      "level": 0,
      "exp": 0
    },
    "smithing": {
      "rank": 0,
      "level": 0,
      "exp": 0
    },
    "mining": {
      "rank": 0,
      "level": 0,
      "exp": 0
    },
    "herblore": {
      "rank": 0,
      "level": 0,
      "exp": 0
    },
    "agility": {
      "rank": 0,
      "level": 0,
      "exp": 0
    },
    "thieving": {
      "rank": 0,
      "level": 0,
      "exp": 0
    },
    "slayer": {
      "rank": 0,
      "level": 0,
      "exp": 0
    },
    "farming": {
      "rank": 0,
      "level": 0,
      "exp": 0
    },
    "runecrafting": {
      "rank": 0,
      "level": 0,
      "exp": 0
    },
    "hunter": {
      "rank": 0,
      "level": 0,
      "exp": 0
    },
    "construction": {
      "rank": 0,
      "level": 0,
      "exp": 0
    },
    "summoning": {
      "rank": 0,
      "level": 0,
      "exp": 0
    },
    "dungeoneering": {
      "rank": 0,
      "level": 0,
      "exp": 0
    },
    "divination": {
      "rank": 0,
      "level": 0,
      "exp": 0
    },
    "invention": {
      "rank": 0,
      "level": 0,
      "exp": 0
    },
    "bounty_hunter": {
      "rank": 0,
      "score": 0
    },
    "bounty_hunter_rouges": {
      "rank": 0,
      "score": 0
    },
    "dominion_tower": {
      "rank": 0,
      "score": 0
    },
    "crucible": {
      "rank": 0,
      "score": 0
    },
    "castle_wars": {
      "rank": 0,
      "score": 0
    },
    "BA_attackers": {
      "rank": 0,
      "score": 0
    },
    "BA_defenders": {
      "rank": 0,
      "score": 0
    },
    "BA_collectors": {
      "rank": 0,
      "score": 0
    },
    "BA_healers": {
      "rank": 0,
      "score": 0
    },
    "duel_tournaments": {
      "rank": 0,
      "score": 0
    },
    "mobilising_armies": {
      "rank": 0,
      "score": 0
    },
    "conquest": {
      "rank": 0,
      "score": 0
    },
    "fist_of_guthix": {
      "rank": 0,
      "score": 0
    },
    "GG_resource": {
      "rank": 0,
      "score": 0
    },
    "GG_athletics": {
      "rank": 0,
      "score": 0
    },
    "we2": {
      "rank": 0,
      "score": 0
    },
    "heist_guard": {
      "rank": 0,
      "score": 0
    },
    "heist_robber": {
      "rank": 0,
      "score": 0
    },
    "CFP": {
      "rank": 0,
      "score": 0
    }
  },
  {
    "rsn": "DNA_Legend",
    "overall": {
      "rank": 0,
      "level": 0,
      "exp": 0
    },
    "attack": {
      "rank": 0,
      "level": 0,
      "exp": 0
    },
    "defence": {
      "rank": 0,
      "level": 0,
      "exp": 0
    },
    "strength": {
      "rank": 0,
      "level": 0,
      "exp": 0
    },
    "constitution": {
      "rank": 0,
      "level": 0,
      "exp": 0
    },
    "ranged": {
      "rank": 0,
      "level": 0,
      "exp": 0
    },
    "prayer": {
      "rank": 0,
      "level": 0,
      "exp": 0
    },
    "magic": {
      "rank": 0,
      "level": 0,
      "exp": 0
    },
    "cooking": {
      "rank": 0,
      "level": 0,
      "exp": 0
    },
    "woodcutting": {
      "rank": 0,
      "level": 0,
      "exp": 0
    },
    "fletching": {
      "rank": 0,
      "level": 0,
      "exp": 0
    },
    "fishing": {
      "rank": 0,
      "level": 0,
      "exp": 0
    },
    "firemaking": {
      "rank": 0,
      "level": 0,
      "exp": 0
    },
    "crafting": {
      "rank": 0,
      "level": 0,
      "exp": 0
    },
    "smithing": {
      "rank": 0,
      "level": 0,
      "exp": 0
    },
    "mining": {
      "rank": 0,
      "level": 0,
      "exp": 0
    },
    "herblore": {
      "rank": 0,
      "level": 0,
      "exp": 0
    },
    "agility": {
      "rank": 0,
      "level": 0,
      "exp": 0
    },
    "thieving": {
      "rank": 0,
      "level": 0,
      "exp": 0
    },
    "slayer": {
      "rank": 0,
      "level": 0,
      "exp": 0
    },
    "farming": {
      "rank": 0,
      "level": 0,
      "exp": 0
    },
    "runecrafting": {
      "rank": 0,
      "level": 0,
      "exp": 0
    },
    "hunter": {
      "rank": 0,
      "level": 0,
      "exp": 0
    },
    "construction": {
      "rank": 0,
      "level": 0,
      "exp": 0
    },
    "summoning": {
      "rank": 0,
      "level": 0,
      "exp": 0
    },
    "dungeoneering": {
      "rank": 0,
      "level": 0,
      "exp": 0
    },
    "divination": {
      "rank": 0,
      "level": 0,
      "exp": 0
    },
    "invention": {
      "rank": 0,
      "level": 0,
      "exp": 0
    },
    "bounty_hunter": {
      "rank": 0,
      "score": 0
    },
    "bounty_hunter_rouges": {
      "rank": 0,
      "score": 0
    },
    "dominion_tower": {
      "rank": 0,
      "score": 0
    },
    "crucible": {
      "rank": 0,
      "score": 0
    },
    "castle_wars": {
      "rank": 0,
      "score": 0
    },
    "BA_attackers": {
      "rank": 0,
      "score": 0
    },
    "BA_defenders": {
      "rank": 0,
      "score": 0
    },
    "BA_collectors": {
      "rank": 0,
      "score": 0
    },
    "BA_healers": {
      "rank": 0,
      "score": 0
    },
    "duel_tournaments": {
      "rank": 0,
      "score": 0
    },
    "mobilising_armies": {
      "rank": 0,
      "score": 0
    },
    "conquest": {
      "rank": 0,
      "score": 0
    },
    "fist_of_guthix": {
      "rank": 0,
      "score": 0
    },
    "GG_resource": {
      "rank": 0,
      "score": 0
    },
    "GG_athletics": {
      "rank": 0,
      "score": 0
    },
    "we2": {
      "rank": 0,
      "score": 0
    },
    "heist_guard": {
      "rank": 0,
      "score": 0
    },
    "heist_robber": {
      "rank": 0,
      "score": 0
    },
    "CFP": {
      "rank": 0,
      "score": 0
    }
  },
  {
    "rsn": "Marcoktm_pt",
    "overall": {
      "rank": 0,
      "level": 0,
      "exp": 0
    },
    "attack": {
      "rank": 0,
      "level": 0,
      "exp": 0
    },
    "defence": {
      "rank": 0,
      "level": 0,
      "exp": 0
    },
    "strength": {
      "rank": 0,
      "level": 0,
      "exp": 0
    },
    "constitution": {
      "rank": 0,
      "level": 0,
      "exp": 0
    },
    "ranged": {
      "rank": 0,
      "level": 0,
      "exp": 0
    },
    "prayer": {
      "rank": 0,
      "level": 0,
      "exp": 0
    },
    "magic": {
      "rank": 0,
      "level": 0,
      "exp": 0
    },
    "cooking": {
      "rank": 0,
      "level": 0,
      "exp": 0
    },
    "woodcutting": {
      "rank": 0,
      "level": 0,
      "exp": 0
    },
    "fletching": {
      "rank": 0,
      "level": 0,
      "exp": 0
    },
    "fishing": {
      "rank": 0,
      "level": 0,
      "exp": 0
    },
    "firemaking": {
      "rank": 0,
      "level": 0,
      "exp": 0
    },
    "crafting": {
      "rank": 0,
      "level": 0,
      "exp": 0
    },
    "smithing": {
      "rank": 0,
      "level": 0,
      "exp": 0
    },
    "mining": {
      "rank": 0,
      "level": 0,
      "exp": 0
    },
    "herblore": {
      "rank": 0,
      "level": 0,
      "exp": 0
    },
    "agility": {
      "rank": 0,
      "level": 0,
      "exp": 0
    },
    "thieving": {
      "rank": 0,
      "level": 0,
      "exp": 0
    },
    "slayer": {
      "rank": 0,
      "level": 0,
      "exp": 0
    },
    "farming": {
      "rank": 0,
      "level": 0,
      "exp": 0
    },
    "runecrafting": {
      "rank": 0,
      "level": 0,
      "exp": 0
    },
    "hunter": {
      "rank": 0,
      "level": 0,
      "exp": 0
    },
    "construction": {
      "rank": 0,
      "level": 0,
      "exp": 0
    },
    "summoning": {
      "rank": 0,
      "level": 0,
      "exp": 0
    },
    "dungeoneering": {
      "rank": 0,
      "level": 0,
      "exp": 0
    },
    "divination": {
      "rank": 0,
      "level": 0,
      "exp": 0
    },
    "invention": {
      "rank": 0,
      "level": 0,
      "exp": 0
    },
    "bounty_hunter": {
      "rank": 0,
      "score": 0
    },
    "bounty_hunter_rouges": {
      "rank": 0,
      "score": 0
    },
    "dominion_tower": {
      "rank": 0,
      "score": 0
    },
    "crucible": {
      "rank": 0,
      "score": 0
    },
    "castle_wars": {
      "rank": 0,
      "score": 0
    },
    "BA_attackers": {
      "rank": 0,
      "score": 0
    },
    "BA_defenders": {
      "rank": 0,
      "score": 0
    },
    "BA_collectors": {
      "rank": 0,
      "score": 0
    },
    "BA_healers": {
      "rank": 0,
      "score": 0
    },
    "duel_tournaments": {
      "rank": 0,
      "score": 0
    },
    "mobilising_armies": {
      "rank": 0,
      "score": 0
    },
    "conquest": {
      "rank": 0,
      "score": 0
    },
    "fist_of_guthix": {
      "rank": 0,
      "score": 0
    },
    "GG_resource": {
      "rank": 0,
      "score": 0
    },
    "GG_athletics": {
      "rank": 0,
      "score": 0
    },
    "we2": {
      "rank": 0,
      "score": 0
    },
    "heist_guard": {
      "rank": 0,
      "score": 0
    },
    "heist_robber": {
      "rank": 0,
      "score": 0
    },
    "CFP": {
      "rank": 0,
      "score": 0
    }
  },
  {
    "rsn": "Rsn_Expert",
    "overall": {
      "rank": 146299,
      "level": 2292,
      "exp": 393912157
    },
    "attack": {
      "rank": 10658,
      "level": 99,
      "exp": 59634978
    },
    "defence": {
      "rank": 71273,
      "level": 99,
      "exp": 19866974
    },
    "strength": {
      "rank": 14745,
      "level": 99,
      "exp": 49397344
    },
    "constitution": {
      "rank": 28461,
      "level": 99,
      "exp": 57783195
    },
    "ranged": {
      "rank": 29191,
      "level": 99,
      "exp": 39132049
    },
    "prayer": {
      "rank": 96483,
      "level": 99,
      "exp": 13346300
    },
    "magic": {
      "rank": 47034,
      "level": 99,
      "exp": 26431964
    },
    "cooking": {
      "rank": 81568,
      "level": 99,
      "exp": 14239759
    },
    "woodcutting": {
      "rank": 192975,
      "level": 93,
      "exp": 7658183
    },
    "fletching": {
      "rank": 197261,
      "level": 91,
      "exp": 5918588
    },
    "fishing": {
      "rank": 256605,
      "level": 82,
      "exp": 2440335
    },
    "firemaking": {
      "rank": 71242,
      "level": 99,
      "exp": 14340428
    },
    "crafting": {
      "rank": 123311,
      "level": 90,
      "exp": 5701820
    },
    "smithing": {
      "rank": 138797,
      "level": 90,
      "exp": 5543147
    },
    "mining": {
      "rank": 205846,
      "level": 81,
      "exp": 2244040
    },
    "herblore": {
      "rank": 41684,
      "level": 99,
      "exp": 15889873
    },
    "agility": {
      "rank": 170621,
      "level": 80,
      "exp": 2097329
    },
    "thieving": {
      "rank": 152396,
      "level": 79,
      "exp": 1877231
    },
    "slayer": {
      "rank": 80242,
      "level": 99,
      "exp": 14550880
    },
    "farming": {
      "rank": 165443,
      "level": 78,
      "exp": 1712471
    },
    "runecrafting": {
      "rank": 160141,
      "level": 80,
      "exp": 2177158
    },
    "hunter": {
      "rank": 165978,
      "level": 80,
      "exp": 1986507
    },
    "construction": {
      "rank": 174437,
      "level": 80,
      "exp": 1996150
    },
    "summoning": {
      "rank": 43884,
      "level": 99,
      "exp": 14236448
    },
    "dungeoneering": {
      "rank": 90997,
      "level": 99,
      "exp": 13709006
    },
    "divination": {
      "rank": -1,
      "level": 1,
      "exp": -1
    },
    "invention": {
      "rank": -1,
      "level": 0,
      "exp": -1
    },
    "bounty_hunter": {
      "rank": 1821,
      "score": 883
    },
    "bounty_hunter_rouges": {
      "rank": 446,
      "score": 6416
    },
    "dominion_tower": {
      "rank": 17694,
      "score": 4022606
    },
    "crucible": {
      "rank": -1,
      "score": -1
    },
    "castle_wars": {
      "rank": -1,
      "score": -1
    },
    "BA_attackers": {
      "rank": 32448,
      "score": 1761
    },
    "BA_defenders": {
      "rank": 67687,
      "score": 763
    },
    "BA_collectors": {
      "rank": 81825,
      "score": 762
    },
    "BA_healers": {
      "rank": 91558,
      "score": 950
    },
    "duel_tournaments": {
      "rank": 3141,
      "score": 1885
    },
    "mobilising_armies": {
      "rank": -1,
      "score": -1
    },
    "conquest": {
      "rank": 24055,
      "score": 1257
    },
    "fist_of_guthix": {
      "rank": 37172,
      "score": 2416
    },
    "GG_resource": {
      "rank": -1,
      "score": -1
    },
    "GG_athletics": {
      "rank": -1,
      "score": -1
    },
    "we2": {
      "rank": -1,
      "score": -1
    },
    "heist_guard": {
      "rank": -1,
      "score": -1
    },
    "heist_robber": {
      "rank": -1,
      "score": -1
    },
    "CFP": {
      "rank": -1,
      "score": -1
    }
  },
  {
    "rsn": "So_Easy99",
    "overall": {
      "rank": 0,
      "level": 0,
      "exp": 0
    },
    "attack": {
      "rank": 0,
      "level": 0,
      "exp": 0
    },
    "defence": {
      "rank": 0,
      "level": 0,
      "exp": 0
    },
    "strength": {
      "rank": 0,
      "level": 0,
      "exp": 0
    },
    "constitution": {
      "rank": 0,
      "level": 0,
      "exp": 0
    },
    "ranged": {
      "rank": 0,
      "level": 0,
      "exp": 0
    },
    "prayer": {
      "rank": 0,
      "level": 0,
      "exp": 0
    },
    "magic": {
      "rank": 0,
      "level": 0,
      "exp": 0
    },
    "cooking": {
      "rank": 0,
      "level": 0,
      "exp": 0
    },
    "woodcutting": {
      "rank": 0,
      "level": 0,
      "exp": 0
    },
    "fletching": {
      "rank": 0,
      "level": 0,
      "exp": 0
    },
    "fishing": {
      "rank": 0,
      "level": 0,
      "exp": 0
    },
    "firemaking": {
      "rank": 0,
      "level": 0,
      "exp": 0
    },
    "crafting": {
      "rank": 0,
      "level": 0,
      "exp": 0
    },
    "smithing": {
      "rank": 0,
      "level": 0,
      "exp": 0
    },
    "mining": {
      "rank": 0,
      "level": 0,
      "exp": 0
    },
    "herblore": {
      "rank": 0,
      "level": 0,
      "exp": 0
    },
    "agility": {
      "rank": 0,
      "level": 0,
      "exp": 0
    },
    "thieving": {
      "rank": 0,
      "level": 0,
      "exp": 0
    },
    "slayer": {
      "rank": 0,
      "level": 0,
      "exp": 0
    },
    "farming": {
      "rank": 0,
      "level": 0,
      "exp": 0
    },
    "runecrafting": {
      "rank": 0,
      "level": 0,
      "exp": 0
    },
    "hunter": {
      "rank": 0,
      "level": 0,
      "exp": 0
    },
    "construction": {
      "rank": 0,
      "level": 0,
      "exp": 0
    },
    "summoning": {
      "rank": 0,
      "level": 0,
      "exp": 0
    },
    "dungeoneering": {
      "rank": 0,
      "level": 0,
      "exp": 0
    },
    "divination": {
      "rank": 0,
      "level": 0,
      "exp": 0
    },
    "invention": {
      "rank": 0,
      "level": 0,
      "exp": 0
    },
    "bounty_hunter": {
      "rank": 0,
      "score": 0
    },
    "bounty_hunter_rouges": {
      "rank": 0,
      "score": 0
    },
    "dominion_tower": {
      "rank": 0,
      "score": 0
    },
    "crucible": {
      "rank": 0,
      "score": 0
    },
    "castle_wars": {
      "rank": 0,
      "score": 0
    },
    "BA_attackers": {
      "rank": 0,
      "score": 0
    },
    "BA_defenders": {
      "rank": 0,
      "score": 0
    },
    "BA_collectors": {
      "rank": 0,
      "score": 0
    },
    "BA_healers": {
      "rank": 0,
      "score": 0
    },
    "duel_tournaments": {
      "rank": 0,
      "score": 0
    },
    "mobilising_armies": {
      "rank": 0,
      "score": 0
    },
    "conquest": {
      "rank": 0,
      "score": 0
    },
    "fist_of_guthix": {
      "rank": 0,
      "score": 0
    },
    "GG_resource": {
      "rank": 0,
      "score": 0
    },
    "GG_athletics": {
      "rank": 0,
      "score": 0
    },
    "we2": {
      "rank": 0,
      "score": 0
    },
    "heist_guard": {
      "rank": 0,
      "score": 0
    },
    "heist_robber": {
      "rank": 0,
      "score": 0
    },
    "CFP": {
      "rank": 0,
      "score": 0
    }
  },
  {
    "rsn": "Wannabe_Nex",
    "overall": {
      "rank": 0,
      "level": 0,
      "exp": 0
    },
    "attack": {
      "rank": 0,
      "level": 0,
      "exp": 0
    },
    "defence": {
      "rank": 0,
      "level": 0,
      "exp": 0
    },
    "strength": {
      "rank": 0,
      "level": 0,
      "exp": 0
    },
    "constitution": {
      "rank": 0,
      "level": 0,
      "exp": 0
    },
    "ranged": {
      "rank": 0,
      "level": 0,
      "exp": 0
    },
    "prayer": {
      "rank": 0,
      "level": 0,
      "exp": 0
    },
    "magic": {
      "rank": 0,
      "level": 0,
      "exp": 0
    },
    "cooking": {
      "rank": 0,
      "level": 0,
      "exp": 0
    },
    "woodcutting": {
      "rank": 0,
      "level": 0,
      "exp": 0
    },
    "fletching": {
      "rank": 0,
      "level": 0,
      "exp": 0
    },
    "fishing": {
      "rank": 0,
      "level": 0,
      "exp": 0
    },
    "firemaking": {
      "rank": 0,
      "level": 0,
      "exp": 0
    },
    "crafting": {
      "rank": 0,
      "level": 0,
      "exp": 0
    },
    "smithing": {
      "rank": 0,
      "level": 0,
      "exp": 0
    },
    "mining": {
      "rank": 0,
      "level": 0,
      "exp": 0
    },
    "herblore": {
      "rank": 0,
      "level": 0,
      "exp": 0
    },
    "agility": {
      "rank": 0,
      "level": 0,
      "exp": 0
    },
    "thieving": {
      "rank": 0,
      "level": 0,
      "exp": 0
    },
    "slayer": {
      "rank": 0,
      "level": 0,
      "exp": 0
    },
    "farming": {
      "rank": 0,
      "level": 0,
      "exp": 0
    },
    "runecrafting": {
      "rank": 0,
      "level": 0,
      "exp": 0
    },
    "hunter": {
      "rank": 0,
      "level": 0,
      "exp": 0
    },
    "construction": {
      "rank": 0,
      "level": 0,
      "exp": 0
    },
    "summoning": {
      "rank": 0,
      "level": 0,
      "exp": 0
    },
    "dungeoneering": {
      "rank": 0,
      "level": 0,
      "exp": 0
    },
    "divination": {
      "rank": 0,
      "level": 0,
      "exp": 0
    },
    "invention": {
      "rank": 0,
      "level": 0,
      "exp": 0
    },
    "bounty_hunter": {
      "rank": 0,
      "score": 0
    },
    "bounty_hunter_rouges": {
      "rank": 0,
      "score": 0
    },
    "dominion_tower": {
      "rank": 0,
      "score": 0
    },
    "crucible": {
      "rank": 0,
      "score": 0
    },
    "castle_wars": {
      "rank": 0,
      "score": 0
    },
    "BA_attackers": {
      "rank": 0,
      "score": 0
    },
    "BA_defenders": {
      "rank": 0,
      "score": 0
    },
    "BA_collectors": {
      "rank": 0,
      "score": 0
    },
    "BA_healers": {
      "rank": 0,
      "score": 0
    },
    "duel_tournaments": {
      "rank": 0,
      "score": 0
    },
    "mobilising_armies": {
      "rank": 0,
      "score": 0
    },
    "conquest": {
      "rank": 0,
      "score": 0
    },
    "fist_of_guthix": {
      "rank": 0,
      "score": 0
    },
    "GG_resource": {
      "rank": 0,
      "score": 0
    },
    "GG_athletics": {
      "rank": 0,
      "score": 0
    },
    "we2": {
      "rank": 0,
      "score": 0
    },
    "heist_guard": {
      "rank": 0,
      "score": 0
    },
    "heist_robber": {
      "rank": 0,
      "score": 0
    },
    "CFP": {
      "rank": 0,
      "score": 0
    }
  },
  {
    "rsn": "Xefe",
    "overall": {
      "rank": 0,
      "level": 0,
      "exp": 0
    },
    "attack": {
      "rank": 0,
      "level": 0,
      "exp": 0
    },
    "defence": {
      "rank": 0,
      "level": 0,
      "exp": 0
    },
    "strength": {
      "rank": 0,
      "level": 0,
      "exp": 0
    },
    "constitution": {
      "rank": 0,
      "level": 0,
      "exp": 0
    },
    "ranged": {
      "rank": 0,
      "level": 0,
      "exp": 0
    },
    "prayer": {
      "rank": 0,
      "level": 0,
      "exp": 0
    },
    "magic": {
      "rank": 0,
      "level": 0,
      "exp": 0
    },
    "cooking": {
      "rank": 0,
      "level": 0,
      "exp": 0
    },
    "woodcutting": {
      "rank": 0,
      "level": 0,
      "exp": 0
    },
    "fletching": {
      "rank": 0,
      "level": 0,
      "exp": 0
    },
    "fishing": {
      "rank": 0,
      "level": 0,
      "exp": 0
    },
    "firemaking": {
      "rank": 0,
      "level": 0,
      "exp": 0
    },
    "crafting": {
      "rank": 0,
      "level": 0,
      "exp": 0
    },
    "smithing": {
      "rank": 0,
      "level": 0,
      "exp": 0
    },
    "mining": {
      "rank": 0,
      "level": 0,
      "exp": 0
    },
    "herblore": {
      "rank": 0,
      "level": 0,
      "exp": 0
    },
    "agility": {
      "rank": 0,
      "level": 0,
      "exp": 0
    },
    "thieving": {
      "rank": 0,
      "level": 0,
      "exp": 0
    },
    "slayer": {
      "rank": 0,
      "level": 0,
      "exp": 0
    },
    "farming": {
      "rank": 0,
      "level": 0,
      "exp": 0
    },
    "runecrafting": {
      "rank": 0,
      "level": 0,
      "exp": 0
    },
    "hunter": {
      "rank": 0,
      "level": 0,
      "exp": 0
    },
    "construction": {
      "rank": 0,
      "level": 0,
      "exp": 0
    },
    "summoning": {
      "rank": 0,
      "level": 0,
      "exp": 0
    },
    "dungeoneering": {
      "rank": 0,
      "level": 0,
      "exp": 0
    },
    "divination": {
      "rank": 0,
      "level": 0,
      "exp": 0
    },
    "invention": {
      "rank": 0,
      "level": 0,
      "exp": 0
    },
    "bounty_hunter": {
      "rank": 0,
      "score": 0
    },
    "bounty_hunter_rouges": {
      "rank": 0,
      "score": 0
    },
    "dominion_tower": {
      "rank": 0,
      "score": 0
    },
    "crucible": {
      "rank": 0,
      "score": 0
    },
    "castle_wars": {
      "rank": 0,
      "score": 0
    },
    "BA_attackers": {
      "rank": 0,
      "score": 0
    },
    "BA_defenders": {
      "rank": 0,
      "score": 0
    },
    "BA_collectors": {
      "rank": 0,
      "score": 0
    },
    "BA_healers": {
      "rank": 0,
      "score": 0
    },
    "duel_tournaments": {
      "rank": 0,
      "score": 0
    },
    "mobilising_armies": {
      "rank": 0,
      "score": 0
    },
    "conquest": {
      "rank": 0,
      "score": 0
    },
    "fist_of_guthix": {
      "rank": 0,
      "score": 0
    },
    "GG_resource": {
      "rank": 0,
      "score": 0
    },
    "GG_athletics": {
      "rank": 0,
      "score": 0
    },
    "we2": {
      "rank": 0,
      "score": 0
    },
    "heist_guard": {
      "rank": 0,
      "score": 0
    },
    "heist_robber": {
      "rank": 0,
      "score": 0
    },
    "CFP": {
      "rank": 0,
      "score": 0
    }
  },
  {
    "rsn": "Mafv",
    "overall": {
      "rank": 150550,
      "level": 2280,
      "exp": 319981698
    },
    "attack": {
      "rank": 57527,
      "level": 99,
      "exp": 21112402
    },
    "defence": {
      "rank": 93838,
      "level": 99,
      "exp": 16614377
    },
    "strength": {
      "rank": 59122,
      "level": 99,
      "exp": 21589223
    },
    "constitution": {
      "rank": 111624,
      "level": 99,
      "exp": 23382711
    },
    "ranged": {
      "rank": 72200,
      "level": 99,
      "exp": 20173930
    },
    "prayer": {
      "rank": 144360,
      "level": 96,
      "exp": 10099747
    },
    "magic": {
      "rank": 233824,
      "level": 95,
      "exp": 9628153
    },
    "cooking": {
      "rank": 239125,
      "level": 89,
      "exp": 5071621
    },
    "woodcutting": {
      "rank": 44454,
      "level": 99,
      "exp": 16713006
    },
    "fletching": {
      "rank": 1212,
      "level": 99,
      "exp": 106839057
    },
    "fishing": {
      "rank": 193363,
      "level": 87,
      "exp": 4265824
    },
    "firemaking": {
      "rank": 189088,
      "level": 95,
      "exp": 8776374
    },
    "crafting": {
      "rank": 197259,
      "level": 80,
      "exp": 2192666
    },
    "smithing": {
      "rank": 278120,
      "level": 75,
      "exp": 1215457
    },
    "mining": {
      "rank": 223749,
      "level": 80,
      "exp": 2001932
    },
    "herblore": {
      "rank": 141637,
      "level": 96,
      "exp": 10344675
    },
    "agility": {
      "rank": 260218,
      "level": 71,
      "exp": 893300
    },
    "thieving": {
      "rank": 254435,
      "level": 68,
      "exp": 648286
    },
    "slayer": {
      "rank": 138252,
      "level": 94,
      "exp": 8609522
    },
    "farming": {
      "rank": 218360,
      "level": 71,
      "exp": 831808
    },
    "runecrafting": {
      "rank": 162637,
      "level": 80,
      "exp": 2116650
    },
    "hunter": {
      "rank": 133418,
      "level": 83,
      "exp": 2891044
    },
    "construction": {
      "rank": 355523,
      "level": 61,
      "exp": 308229
    },
    "summoning": {
      "rank": 132937,
      "level": 96,
      "exp": 9763102
    },
    "dungeoneering": {
      "rank": 97505,
      "level": 99,
      "exp": 13134773
    },
    "divination": {
      "rank": 207083,
      "level": 70,
      "exp": 763829
    },
    "invention": {
      "rank": -1,
      "level": 0,
      "exp": -1
    },
    "bounty_hunter": {
      "rank": -1,
      "score": -1
    },
    "bounty_hunter_rouges": {
      "rank": -1,
      "score": -1
    },
    "dominion_tower": {
      "rank": -1,
      "score": -1
    },
    "crucible": {
      "rank": -1,
      "score": -1
    },
    "castle_wars": {
      "rank": -1,
      "score": -1
    },
    "BA_attackers": {
      "rank": 10126,
      "score": 2830
    },
    "BA_defenders": {
      "rank": 26358,
      "score": 1478
    },
    "BA_collectors": {
      "rank": 32147,
      "score": 1424
    },
    "BA_healers": {
      "rank": 57220,
      "score": 1501
    },
    "duel_tournaments": {
      "rank": -1,
      "score": -1
    },
    "mobilising_armies": {
      "rank": -1,
      "score": -1
    },
    "conquest": {
      "rank": -1,
      "score": -1
    },
    "fist_of_guthix": {
      "rank": 191419,
      "score": 518
    },
    "GG_resource": {
      "rank": -1,
      "score": -1
    },
    "GG_athletics": {
      "rank": 59656,
      "score": 561
    },
    "we2": {
      "rank": -1,
      "score": -1
    },
    "heist_guard": {
      "rank": -1,
      "score": -1
    },
    "heist_robber": {
      "rank": -1,
      "score": -1
    },
    "CFP": {
      "rank": -1,
      "score": -1
    }
  },
  {
    "rsn": "Natty_Gon",
    "overall": {
      "rank": 0,
      "level": 0,
      "exp": 0
    },
    "attack": {
      "rank": 0,
      "level": 0,
      "exp": 0
    },
    "defence": {
      "rank": 0,
      "level": 0,
      "exp": 0
    },
    "strength": {
      "rank": 0,
      "level": 0,
      "exp": 0
    },
    "constitution": {
      "rank": 0,
      "level": 0,
      "exp": 0
    },
    "ranged": {
      "rank": 0,
      "level": 0,
      "exp": 0
    },
    "prayer": {
      "rank": 0,
      "level": 0,
      "exp": 0
    },
    "magic": {
      "rank": 0,
      "level": 0,
      "exp": 0
    },
    "cooking": {
      "rank": 0,
      "level": 0,
      "exp": 0
    },
    "woodcutting": {
      "rank": 0,
      "level": 0,
      "exp": 0
    },
    "fletching": {
      "rank": 0,
      "level": 0,
      "exp": 0
    },
    "fishing": {
      "rank": 0,
      "level": 0,
      "exp": 0
    },
    "firemaking": {
      "rank": 0,
      "level": 0,
      "exp": 0
    },
    "crafting": {
      "rank": 0,
      "level": 0,
      "exp": 0
    },
    "smithing": {
      "rank": 0,
      "level": 0,
      "exp": 0
    },
    "mining": {
      "rank": 0,
      "level": 0,
      "exp": 0
    },
    "herblore": {
      "rank": 0,
      "level": 0,
      "exp": 0
    },
    "agility": {
      "rank": 0,
      "level": 0,
      "exp": 0
    },
    "thieving": {
      "rank": 0,
      "level": 0,
      "exp": 0
    },
    "slayer": {
      "rank": 0,
      "level": 0,
      "exp": 0
    },
    "farming": {
      "rank": 0,
      "level": 0,
      "exp": 0
    },
    "runecrafting": {
      "rank": 0,
      "level": 0,
      "exp": 0
    },
    "hunter": {
      "rank": 0,
      "level": 0,
      "exp": 0
    },
    "construction": {
      "rank": 0,
      "level": 0,
      "exp": 0
    },
    "summoning": {
      "rank": 0,
      "level": 0,
      "exp": 0
    },
    "dungeoneering": {
      "rank": 0,
      "level": 0,
      "exp": 0
    },
    "divination": {
      "rank": 0,
      "level": 0,
      "exp": 0
    },
    "invention": {
      "rank": 0,
      "level": 0,
      "exp": 0
    },
    "bounty_hunter": {
      "rank": 0,
      "score": 0
    },
    "bounty_hunter_rouges": {
      "rank": 0,
      "score": 0
    },
    "dominion_tower": {
      "rank": 0,
      "score": 0
    },
    "crucible": {
      "rank": 0,
      "score": 0
    },
    "castle_wars": {
      "rank": 0,
      "score": 0
    },
    "BA_attackers": {
      "rank": 0,
      "score": 0
    },
    "BA_defenders": {
      "rank": 0,
      "score": 0
    },
    "BA_collectors": {
      "rank": 0,
      "score": 0
    },
    "BA_healers": {
      "rank": 0,
      "score": 0
    },
    "duel_tournaments": {
      "rank": 0,
      "score": 0
    },
    "mobilising_armies": {
      "rank": 0,
      "score": 0
    },
    "conquest": {
      "rank": 0,
      "score": 0
    },
    "fist_of_guthix": {
      "rank": 0,
      "score": 0
    },
    "GG_resource": {
      "rank": 0,
      "score": 0
    },
    "GG_athletics": {
      "rank": 0,
      "score": 0
    },
    "we2": {
      "rank": 0,
      "score": 0
    },
    "heist_guard": {
      "rank": 0,
      "score": 0
    },
    "heist_robber": {
      "rank": 0,
      "score": 0
    },
    "CFP": {
      "rank": 0,
      "score": 0
    }
  }
]