[{"rsn":"Sael","overall":{"rank":49266,"level":2426,"exp":281215260,"isSkill":true},"attack":{"rank":65359,"level":99,"exp":16980873,"isSkill":true},"defence":{"rank":57916,"level":99,"exp":16785964,"isSkill":true},"strength":{"rank":57375,"level":99,"exp":19904288,"isSkill":true},"constitution":{"rank":62901,"level":99,"exp":24681292,"isSkill":true},"ranged":{"rank":58004,"level":99,"exp":16026999,"isSkill":true},"prayer":{"rank":94744,"level":96,"exp":9700820,"isSkill":true},"magic":{"rank":79649,"level":99,"exp":14885568,"isSkill":true},"cooking":{"rank":6397,"level":99,"exp":26568870,"isSkill":true},"woodcutting":{"rank":58421,"level":99,"exp":14476113,"isSkill":true},"fletching":{"rank":9600,"level":99,"exp":17094112,"isSkill":true},"fishing":{"rank":120494,"level":92,"exp":6944009,"isSkill":true},"firemaking":{"rank":31236,"level":99,"exp":14874331,"isSkill":true},"crafting":{"rank":76178,"level":90,"exp":5420015,"isSkill":true},"smithing":{"rank":92775,"level":87,"exp":4279159,"isSkill":true},"mining":{"rank":126995,"level":85,"exp":3303401,"isSkill":true},"herblore":{"rank":115307,"level":92,"exp":6780905,"isSkill":true},"agility":{"rank":74577,"level":86,"exp":3866146,"isSkill":true},"thieving":{"rank":103326,"level":81,"exp":2383968,"isSkill":true},"slayer":{"rank":41523,"level":99,"exp":13394168,"isSkill":true},"farming":{"rank":51679,"level":94,"exp":8550892,"isSkill":true},"runecrafting":{"rank":73443,"level":92,"exp":6556534,"isSkill":true},"hunter":{"rank":94395,"level":84,"exp":3018349,"isSkill":true},"construction":{"rank":45755,"level":94,"exp":8364595,"isSkill":true},"summoning":{"rank":68705,"level":96,"exp":10023259,"isSkill":true},"dungeoneering":{"rank":137411,"level":87,"exp":4064062,"isSkill":true},"divination":{"rank":59160,"level":81,"exp":2286568,"isSkill":true},"bounty_hunter":{"rank":-1,"score":-1,"isSkill":false},"bounty_hunter_rouges":{"rank":-1,"score":-1,"isSkill":false},"dominion_tower":{"rank":-1,"score":-1,"isSkill":false},"crucible":{"rank":-1,"score":-1,"isSkill":false},"castle_wars":{"rank":-1,"score":-1,"isSkill":false},"BA_attackers":{"rank":89223,"score":905,"isSkill":false},"BA_defenders":{"rank":86530,"score":703,"isSkill":false},"BA_collectors":{"rank":86539,"score":799,"isSkill":false},"BA_healers":{"rank":142435,"score":706,"isSkill":false},"duel_tournaments":{"rank":-1,"score":-1,"isSkill":false},"mobilising_armies":{"rank":-1,"score":-1,"isSkill":false},"conquest":{"rank":-1,"score":-1,"isSkill":false},"fist_of_guthix":{"rank":834,"score":22321,"isSkill":false},"GG_resource":{"rank":2798,"score":700,"isSkill":false},"GG_athletics":{"rank":2412,"score":622,"isSkill":false},"we2":{"rank":-1,"score":-1,"isSkill":false},"heist_guard":{"rank":-1,"score":-1,"isSkill":false},"heist_robber":{"rank":-1,"score":-1,"isSkill":false},"CFP":{"rank":-1,"score":-1,"isSkill":false}},{"rsn":"Eiwa","overall":{"rank":70848,"level":2340,"exp":222602075,"isSkill":true},"attack":{"rank":111081,"level":99,"exp":13602907,"isSkill":true},"defence":{"rank":63262,"level":99,"exp":16167548,"isSkill":true},"strength":{"rank":118274,"level":99,"exp":14136242,"isSkill":true},"constitution":{"rank":82808,"level":99,"exp":21119871,"isSkill":true},"ranged":{"rank":150580,"level":94,"exp":8761892,"isSkill":true},"prayer":{"rank":95649,"level":95,"exp":9630130,"isSkill":true},"magic":{"rank":64681,"level":99,"exp":16002394,"isSkill":true},"cooking":{"rank":80193,"level":99,"exp":13790084,"isSkill":true},"woodcutting":{"rank":202750,"level":91,"exp":6418495,"isSkill":true},"fletching":{"rank":47925,"level":99,"exp":13694030,"isSkill":true},"fishing":{"rank":182998,"level":86,"exp":3734703,"isSkill":true},"firemaking":{"rank":83932,"level":99,"exp":13260322,"isSkill":true},"crafting":{"rank":109639,"level":82,"exp":2656369,"isSkill":true},"smithing":{"rank":66885,"level":91,"exp":6360746,"isSkill":true},"mining":{"rank":88809,"level":89,"exp":4970523,"isSkill":true},"herblore":{"rank":183314,"level":78,"exp":1636132,"isSkill":true},"agility":{"rank":158651,"level":75,"exp":1291729,"isSkill":true},"thieving":{"rank":111474,"level":80,"exp":2108649,"isSkill":true},"slayer":{"rank":57398,"level":97,"exp":11545401,"isSkill":true},"farming":{"rank":133347,"level":76,"exp":1471917,"isSkill":true},"runecrafting":{"rank":144262,"level":80,"exp":2023014,"isSkill":true},"hunter":{"rank":100434,"level":83,"exp":2751094,"isSkill":true},"construction":{"rank":137319,"level":76,"exp":1456233,"isSkill":true},"summoning":{"rank":56039,"level":99,"exp":13053574,"isSkill":true},"dungeoneering":{"rank":43530,"level":103,"exp":19948072,"isSkill":true},"divination":{"rank":92088,"level":73,"exp":1010004,"isSkill":true},"bounty_hunter":{"rank":-1,"score":-1,"isSkill":false},"bounty_hunter_rouges":{"rank":-1,"score":-1,"isSkill":false},"dominion_tower":{"rank":-1,"score":-1,"isSkill":false},"crucible":{"rank":-1,"score":-1,"isSkill":false},"castle_wars":{"rank":-1,"score":-1,"isSkill":false},"BA_attackers":{"rank":53750,"score":1331,"isSkill":false},"BA_defenders":{"rank":29164,"score":1446,"isSkill":false},"BA_collectors":{"rank":36776,"score":1373,"isSkill":false},"BA_healers":{"rank":28529,"score":2319,"isSkill":false},"duel_tournaments":{"rank":-1,"score":-1,"isSkill":false},"mobilising_armies":{"rank":-1,"score":-1,"isSkill":false},"conquest":{"rank":-1,"score":-1,"isSkill":false},"fist_of_guthix":{"rank":24121,"score":3528,"isSkill":false},"GG_resource":{"rank":25729,"score":434,"isSkill":false},"GG_athletics":{"rank":102309,"score":550,"isSkill":false},"we2":{"rank":-1,"score":-1,"isSkill":false},"heist_guard":{"rank":-1,"score":-1,"isSkill":false},"heist_robber":{"rank":-1,"score":-1,"isSkill":false},"CFP":{"rank":-1,"score":-1,"isSkill":false}},{"rsn":"Asheka","overall":{"rank":159890,"level":2094,"exp":62990989,"isSkill":true},"attack":{"rank":412080,"level":79,"exp":1887728,"isSkill":true},"defence":{"rank":359110,"level":80,"exp":2019732,"isSkill":true},"strength":{"rank":345176,"level":85,"exp":3506222,"isSkill":true},"constitution":{"rank":377390,"level":84,"exp":3187935,"isSkill":true},"ranged":{"rank":278615,"level":83,"exp":2800084,"isSkill":true},"prayer":{"rank":247604,"level":74,"exp":1129826,"isSkill":true},"magic":{"rank":277840,"level":89,"exp":5265128,"isSkill":true},"cooking":{"rank":226212,"level":90,"exp":5378075,"isSkill":true},"woodcutting":{"rank":390299,"level":81,"exp":2300149,"isSkill":true},"fletching":{"rank":303335,"level":80,"exp":2067313,"isSkill":true},"fishing":{"rank":279712,"level":80,"exp":1990236,"isSkill":true},"firemaking":{"rank":182927,"level":90,"exp":5632488,"isSkill":true},"crafting":{"rank":145771,"level":79,"exp":1871260,"isSkill":true},"smithing":{"rank":116115,"level":83,"exp":2769391,"isSkill":true},"mining":{"rank":176588,"level":80,"exp":2123563,"isSkill":true},"herblore":{"rank":207989,"level":73,"exp":1027630,"isSkill":true},"agility":{"rank":126312,"level":79,"exp":1814896,"isSkill":true},"thieving":{"rank":129823,"level":77,"exp":1623360,"isSkill":true},"slayer":{"rank":216524,"level":77,"exp":1539145,"isSkill":true},"farming":{"rank":115428,"level":80,"exp":2020251,"isSkill":true},"runecrafting":{"rank":157544,"level":78,"exp":1697727,"isSkill":true},"hunter":{"rank":151055,"level":76,"exp":1406814,"isSkill":true},"construction":{"rank":134747,"level":77,"exp":1499269,"isSkill":true},"summoning":{"rank":153419,"level":80,"exp":2094513,"isSkill":true},"dungeoneering":{"rank":170510,"level":83,"exp":2793508,"isSkill":true},"divination":{"rank":75466,"level":77,"exp":1544746,"isSkill":true},"bounty_hunter":{"rank":-1,"score":-1,"isSkill":false},"bounty_hunter_rouges":{"rank":-1,"score":-1,"isSkill":false},"dominion_tower":{"rank":-1,"score":-1,"isSkill":false},"crucible":{"rank":-1,"score":-1,"isSkill":false},"castle_wars":{"rank":-1,"score":-1,"isSkill":false},"BA_attackers":{"rank":-1,"score":-1,"isSkill":false},"BA_defenders":{"rank":-1,"score":-1,"isSkill":false},"BA_collectors":{"rank":-1,"score":-1,"isSkill":false},"BA_healers":{"rank":-1,"score":-1,"isSkill":false},"duel_tournaments":{"rank":-1,"score":-1,"isSkill":false},"mobilising_armies":{"rank":-1,"score":-1,"isSkill":false},"conquest":{"rank":-1,"score":-1,"isSkill":false},"fist_of_guthix":{"rank":-1,"score":-1,"isSkill":false},"GG_resource":{"rank":-1,"score":-1,"isSkill":false},"GG_athletics":{"rank":68518,"score":561,"isSkill":false},"we2":{"rank":-1,"score":-1,"isSkill":false},"heist_guard":{"rank":-1,"score":-1,"isSkill":false},"heist_robber":{"rank":-1,"score":-1,"isSkill":false},"CFP":{"rank":-1,"score":-1,"isSkill":false}},{"rsn":"Supersongoko","overall":{"rank":10660,"level":2594,"exp":1279539577,"isSkill":true},"attack":{"rank":13321,"level":99,"exp":34521507,"isSkill":true},"defence":{"rank":9391,"level":99,"exp":36164529,"isSkill":true},"strength":{"rank":10323,"level":99,"exp":44565567,"isSkill":true},"constitution":{"rank":9470,"level":99,"exp":52973313,"isSkill":true},"ranged":{"rank":8128,"level":99,"exp":33336351,"isSkill":true},"prayer":{"rank":551,"level":99,"exp":34335247,"isSkill":true},"magic":{"rank":7663,"level":99,"exp":37406348,"isSkill":true},"cooking":{"rank":222,"level":99,"exp":200000000,"isSkill":true},"woodcutting":{"rank":818,"level":99,"exp":63535640,"isSkill":true},"fletching":{"rank":860,"level":99,"exp":46727176,"isSkill":true},"fishing":{"rank":6929,"level":99,"exp":23907155,"isSkill":true},"firemaking":{"rank":2995,"level":99,"exp":36117719,"isSkill":true},"crafting":{"rank":566,"level":99,"exp":34257153,"isSkill":true},"smithing":{"rank":707,"level":99,"exp":31487867,"isSkill":true},"mining":{"rank":2693,"level":99,"exp":25686911,"isSkill":true},"herblore":{"rank":1400,"level":99,"exp":31704165,"isSkill":true},"agility":{"rank":916,"level":99,"exp":27381019,"isSkill":true},"thieving":{"rank":413,"level":99,"exp":56458478,"isSkill":true},"slayer":{"rank":4266,"level":99,"exp":27874667,"isSkill":true},"farming":{"rank":649,"level":99,"exp":59407398,"isSkill":true},"runecrafting":{"rank":1323,"level":99,"exp":31132014,"isSkill":true},"hunter":{"rank":1131,"level":99,"exp":34290975,"isSkill":true},"construction":{"rank":612,"level":99,"exp":31981118,"isSkill":true},"summoning":{"rank":1654,"level":99,"exp":32481397,"isSkill":true},"dungeoneering":{"rank":54,"level":120,"exp":200000000,"isSkill":true},"divination":{"rank":24144,"level":98,"exp":11805863,"isSkill":true},"bounty_hunter":{"rank":-1,"score":-1,"isSkill":false},"bounty_hunter_rouges":{"rank":-1,"score":-1,"isSkill":false},"dominion_tower":{"rank":9411,"score":4411777,"isSkill":false},"crucible":{"rank":-1,"score":-1,"isSkill":false},"castle_wars":{"rank":-1,"score":-1,"isSkill":false},"BA_attackers":{"rank":157819,"score":552,"isSkill":false},"BA_defenders":{"rank":81795,"score":746,"isSkill":false},"BA_collectors":{"rank":-1,"score":-1,"isSkill":false},"BA_healers":{"rank":-1,"score":-1,"isSkill":false},"duel_tournaments":{"rank":4692,"score":1864,"isSkill":false},"mobilising_armies":{"rank":-1,"score":-1,"isSkill":false},"conquest":{"rank":-1,"score":-1,"isSkill":false},"fist_of_guthix":{"rank":-1,"score":-1,"isSkill":false},"GG_resource":{"rank":54479,"score":286,"isSkill":false},"GG_athletics":{"rank":103148,"score":550,"isSkill":false},"we2":{"rank":-1,"score":-1,"isSkill":false},"heist_guard":{"rank":-1,"score":-1,"isSkill":false},"heist_robber":{"rank":-1,"score":-1,"isSkill":false},"CFP":{"rank":70624,"score":15,"isSkill":false}},{"rsn":"Broa","overall":{"rank":106192,"level":2229,"exp":114725958,"isSkill":true},"attack":{"rank":222384,"level":90,"exp":5476567,"isSkill":true},"defence":{"rank":283741,"level":84,"exp":3138329,"isSkill":true},"strength":{"rank":240907,"level":92,"exp":7019142,"isSkill":true},"constitution":{"rank":225044,"level":94,"exp":8211632,"isSkill":true},"ranged":{"rank":202607,"level":89,"exp":5284059,"isSkill":true},"prayer":{"rank":100359,"level":95,"exp":9356061,"isSkill":true},"magic":{"rank":189663,"level":96,"exp":10437335,"isSkill":true},"cooking":{"rank":227096,"level":90,"exp":5359751,"isSkill":true},"woodcutting":{"rank":425615,"level":80,"exp":2025793,"isSkill":true},"fletching":{"rank":200381,"level":88,"exp":4631309,"isSkill":true},"fishing":{"rank":149885,"level":90,"exp":5410397,"isSkill":true},"firemaking":{"rank":172427,"level":92,"exp":6592375,"isSkill":true},"crafting":{"rank":117560,"level":81,"exp":2387197,"isSkill":true},"smithing":{"rank":84993,"level":90,"exp":5346501,"isSkill":true},"mining":{"rank":187053,"level":80,"exp":2005337,"isSkill":true},"herblore":{"rank":130027,"level":90,"exp":5372464,"isSkill":true},"agility":{"rank":110629,"level":80,"exp":2091371,"isSkill":true},"thieving":{"rank":154769,"level":75,"exp":1223274,"isSkill":true},"slayer":{"rank":182040,"level":81,"exp":2243701,"isSkill":true},"farming":{"rank":184807,"level":70,"exp":779572,"isSkill":true},"runecrafting":{"rank":123743,"level":82,"exp":2488372,"isSkill":true},"hunter":{"rank":84600,"level":86,"exp":3603448,"isSkill":true},"construction":{"rank":147153,"level":75,"exp":1329496,"isSkill":true},"summoning":{"rank":98738,"level":90,"exp":5407882,"isSkill":true},"dungeoneering":{"rank":112216,"level":90,"exp":5697626,"isSkill":true},"divination":{"rank":69633,"level":79,"exp":1806967,"isSkill":true},"bounty_hunter":{"rank":-1,"score":-1,"isSkill":false},"bounty_hunter_rouges":{"rank":-1,"score":-1,"isSkill":false},"dominion_tower":{"rank":39778,"score":1822771,"isSkill":false},"crucible":{"rank":-1,"score":-1,"isSkill":false},"castle_wars":{"rank":-1,"score":-1,"isSkill":false},"BA_attackers":{"rank":-1,"score":-1,"isSkill":false},"BA_defenders":{"rank":-1,"score":-1,"isSkill":false},"BA_collectors":{"rank":-1,"score":-1,"isSkill":false},"BA_healers":{"rank":-1,"score":-1,"isSkill":false},"duel_tournaments":{"rank":-1,"score":-1,"isSkill":false},"mobilising_armies":{"rank":-1,"score":-1,"isSkill":false},"conquest":{"rank":-1,"score":-1,"isSkill":false},"fist_of_guthix":{"rank":-1,"score":-1,"isSkill":false},"GG_resource":{"rank":23486,"score":450,"isSkill":false},"GG_athletics":{"rank":126600,"score":544,"isSkill":false},"we2":{"rank":-1,"score":-1,"isSkill":false},"heist_guard":{"rank":-1,"score":-1,"isSkill":false},"heist_robber":{"rank":-1,"score":-1,"isSkill":false},"CFP":{"rank":-1,"score":-1,"isSkill":false}},{"rsn":"Akirahh","overall":{"rank":777646,"level":965,"exp":2950850,"isSkill":true},"attack":{"rank":962914,"level":51,"exp":120869,"isSkill":true},"defence":{"rank":920361,"level":51,"exp":120989,"isSkill":true},"strength":{"rank":1017470,"level":51,"exp":120845,"isSkill":true},"constitution":{"rank":1018882,"level":52,"exp":133994,"isSkill":true},"ranged":{"rank":993258,"level":37,"exp":27524,"isSkill":true},"prayer":{"rank":1019965,"level":30,"exp":14035,"isSkill":true},"magic":{"rank":1079969,"level":37,"exp":29636,"isSkill":true},"cooking":{"rank":678111,"level":60,"exp":278258,"isSkill":true},"woodcutting":{"rank":728598,"level":66,"exp":498299,"isSkill":true},"fletching":{"rank":649124,"level":50,"exp":101925,"isSkill":true},"fishing":{"rank":657943,"level":60,"exp":277848,"isSkill":true},"firemaking":{"rank":544860,"level":64,"exp":427427,"isSkill":true},"crafting":{"rank":632139,"level":50,"exp":110781,"isSkill":true},"smithing":{"rank":673385,"level":50,"exp":102416,"isSkill":true},"mining":{"rank":628059,"level":60,"exp":275150,"isSkill":true},"herblore":{"rank":-1,"level":1,"exp":-1,"isSkill":true},"agility":{"rank":833924,"level":25,"exp":8401,"isSkill":true},"thieving":{"rank":874221,"level":19,"exp":4051,"isSkill":true},"slayer":{"rank":703307,"level":29,"exp":13188,"isSkill":true},"farming":{"rank":652379,"level":15,"exp":2507,"isSkill":true},"runecrafting":{"rank":357358,"level":60,"exp":276729,"isSkill":true},"hunter":{"rank":-1,"level":1,"exp":-1,"isSkill":true},"construction":{"rank":-1,"level":1,"exp":-1,"isSkill":true},"summoning":{"rank":-1,"level":1,"exp":-1,"isSkill":true},"dungeoneering":{"rank":-1,"level":1,"exp":-1,"isSkill":true},"divination":{"rank":320991,"level":15,"exp":2505,"isSkill":true},"bounty_hunter":{"rank":-1,"score":-1,"isSkill":false},"bounty_hunter_rouges":{"rank":-1,"score":-1,"isSkill":false},"dominion_tower":{"rank":-1,"score":-1,"isSkill":false},"crucible":{"rank":-1,"score":-1,"isSkill":false},"castle_wars":{"rank":-1,"score":-1,"isSkill":false},"BA_attackers":{"rank":-1,"score":-1,"isSkill":false},"BA_defenders":{"rank":-1,"score":-1,"isSkill":false},"BA_collectors":{"rank":-1,"score":-1,"isSkill":false},"BA_healers":{"rank":-1,"score":-1,"isSkill":false},"duel_tournaments":{"rank":-1,"score":-1,"isSkill":false},"mobilising_armies":{"rank":-1,"score":-1,"isSkill":false},"conquest":{"rank":-1,"score":-1,"isSkill":false},"fist_of_guthix":{"rank":-1,"score":-1,"isSkill":false},"GG_resource":{"rank":-1,"score":-1,"isSkill":false},"GG_athletics":{"rank":-1,"score":-1,"isSkill":false},"we2":{"rank":-1,"score":-1,"isSkill":false},"heist_guard":{"rank":-1,"score":-1,"isSkill":false},"heist_robber":{"rank":-1,"score":-1,"isSkill":false},"CFP":{"rank":-1,"score":-1,"isSkill":false}}]